{"finalizado": true, "mensaje": "\u00a1Registro(s) obtenido(s) con \u00e9xito!", "datos": {"total": 103527, "filas": [{"id": "54224", "codigo": "PUBC6N102285", "titulo": "CONSTITUCI\u00d3N DE SOCIEDAD COMERCIAL S.R.L. SOCIEDAD COLECTIVA O SOCIEDAD EN COMANDITA SIMPLE", "resumen": "TESTIMONIO DE CONSTITUCION DE RESPONSABILIDAD LIMITADA", "fechaPublicacion": "2017-08-31T04:00:00.000Z", "empresa": {"matricula": null, "matriculaAnterior": "00374138", "razonSocial": "PGEOF S.R.L. PLANIFICACION Y GESTION ESTRATEGICA S.R.L."}, "fechaPublicacionFormato": "2017/08/31"}, {"id": "54219", "codigo": "PUBKKXL02262", "titulo": "CONSTITUCI\u00d3N DE SOCIEDAD COMERCIAL S.R.L. SOCIEDAD COLECTIVA O SOCIEDAD EN COMANDITA SIMPLE", "resumen": "TESTIMONIO DE CONSTITUCION DE SOCIEDAD DE RESPONSABILIDAD LIMITADA", "fechaPublicacion": "2017-08-31T04:00:00.000Z", "empresa": {"matricula": "344028028", "matriculaAnterior": "00374121", "razonSocial": "TRANSPORT SELLER S.R.L."}, "fechaPublicacionFormato": "2017/08/31"}, {"id": "54207", "codigo": "PUBHAVP02256", "titulo": "CONSTITUCI\u00d3N DE SOCIEDAD COMERCIAL S.R.L. SOCIEDAD COLECTIVA O SOCIEDAD EN COMANDITA SIMPLE", "resumen": "TESTIMONIO DE CONSTITUCION DE SOCIEDAD DE RESPONSABILIDAD LIMITADA.", "fechaPublicacion": "2017-08-31T04:00:00.000Z", "empresa": {"matricula": "344844020", "matriculaAnterior": "00374098", "razonSocial": "EMPRESA DE TRANSPORTE DE CARGA NACIONAL E INTERNACIONAL ETYMAR        S.R.L."}, "fechaPublicacionFormato": "2017/08/31"}, {"id": "54201", "codigo": "PUB6QSU02239", "titulo": "CONSTITUCI\u00d3N DE SOCIEDAD COMERCIAL S.R.L. SOCIEDAD COLECTIVA O SOCIEDAD EN COMANDITA SIMPLE", "resumen": "TESTIMONIO DE CONSTITUCION DE SOCIEDAD DE RESPONSABILIDAD LIMITADA.", "fechaPublicacion": "2017-08-31T04:00:00.000Z", "empresa": {"matricula": "344008027", "matriculaAnterior": "00374089", "razonSocial": "ANYDAR INGENIERIA S.R.L."}, "fechaPublicacionFormato": "2017/08/31"}, {"id": "54206", "codigo": "PUB2LTW02255", "titulo": "CONSTITUCI\u00d3N DE SOCIEDAD COMERCIAL S.R.L. SOCIEDAD COLECTIVA O SOCIEDAD EN COMANDITA SIMPLE", "resumen": "TESTIMONIO DE CONSTITUCION DE SOCIEDAD COMERCIAL", "fechaPublicacion": "2017-08-31T04:00:00.000Z", "empresa": {"matricula": "343372029", "matriculaAnterior": "00374097", "razonSocial": "ASESORAMIENTO LEGAL CONTABLE Y TRIBUTARIO - ALCONT S.R.L."}, "fechaPublicacionFormato": "2017/08/31"}, {"id": "26239", "codigo": "PUBH4DP02253", "titulo": "TRANSFERENCIA DE CUOTAS DE CAPITAL", "resumen": "TRANSFERENCIA DE CUOTAS DE CAPITAL, ADMISION DE NUEVOS SOCIOS.", "fechaPublicacion": "2017-08-31T04:00:00.000Z", "empresa": {"matricula": "136811026", "matriculaAnterior": "00192343", "razonSocial": "EDIFICIO EXPRINCESA S.R.L."}, "fechaPublicacionFormato": "2017/08/31"}, {"id": "36719", "codigo": "PUBR41K02296", "titulo": "AUMENTO DE CAPITAL SOCIAL", "resumen": "TESTIMONIO DE ESCRITURA PUBLICA DE AUMENTO DE CAPITAL SOCIAL A LA SUMA DE BS. 490,000.- Y CONSIGUIENTE MODIFICACION DE ESCRITURA CONSTITUTIVA", "fechaPublicacion": "2017-08-31T04:00:00.000Z", "empresa": {"matricula": "281948020", "matriculaAnterior": "00300764", "razonSocial": "CONSULTORA Y CONSTRUCTORA ANGELA ATAHUACHI BAUTISTA S.R.L."}, "fechaPublicacionFormato": "2017/08/31"}, {"id": "54211", "codigo": "PUBRVMO02258", "titulo": "CONSTITUCI\u00d3N DE SOCIEDAD COMERCIAL S.R.L. SOCIEDAD COLECTIVA O SOCIEDAD EN COMANDITA SIMPLE", "resumen": "TESTIMONIO DE CONSTITUCION DE SOCIEDAD DE RESPONSABILIDAD LIMITADA", "fechaPublicacion": "2017-08-31T04:00:00.000Z", "empresa": {"matricula": "345898025", "matriculaAnterior": "00374105", "razonSocial": "ECOSERTEC S.R.L."}, "fechaPublicacionFormato": "2017/08/31"}, {"id": "7985", "codigo": "PUBC83702251", "titulo": "PUBLICACI\u00d3N DE LA MEMORIA ANUAL DE LA SOCIEDAD: AGROINDUSTRIAS LOCHMANN S.A.", "resumen": "PUBLICACI\u00d3N DE LA MEMORIA ANUAL DE LA SOCIEDAD: AGROINDUSTRIAS LOCHMANN S.A. DE LA GESTI\u00d3N: 2014", "fechaPublicacion": "2017-08-31T04:00:00.000Z", "empresa": {"matricula": "1024705020", "matriculaAnterior": "00013906", "razonSocial": "AGROINDUSTRIAS LOCHMANN S.A."}, "fechaPublicacionFormato": "2017/08/31"}, {"id": "7984", "codigo": "PUBP99102254", "titulo": "PUBLICACI\u00d3N DE LA MEMORIA ANUAL DE LA SOCIEDAD: AGROINDUSTRIAS LOCHMANN S.A.", "resumen": "PUBLICACI\u00d3N DE LA MEMORIA ANUAL DE LA SOCIEDAD: AGROINDUSTRIAS LOCHMANN S.A. DE LA GESTI\u00d3N: 2016", "fechaPublicacion": "2017-08-31T04:00:00.000Z", "empresa": {"matricula": "1024705020", "matriculaAnterior": "00013906", "razonSocial": "AGROINDUSTRIAS LOCHMANN S.A."}, "fechaPublicacionFormato": "2017/08/31"}, {"id": "54199", "codigo": "PUB7C2D02237", "titulo": "CONSTITUCI\u00d3N DE SOCIEDAD COMERCIAL S.A., SOCIEDAD EN COMANDITA POR ACCIONES CONSTITUIDAS POR ACTO \u00daNICO, POR SUSCRIPCI\u00d3N P\u00daBLICA DE ACCIONES O CONSTITUCI\u00d3N DE SOCIEDAD DE ECONOM\u00cdA MIXTA", "resumen": "TESTIMONIO DE CONSTITUCION DE SOCIEDAD ANONIMA", "fechaPublicacion": "2017-08-31T04:00:00.000Z", "empresa": {"matricula": "343192029", "matriculaAnterior": "00374088", "razonSocial": "ACERVO INVERSIONES S.A."}, "fechaPublicacionFormato": "2017/08/31"}, {"id": "7983", "codigo": "PUB5CHO02252", "titulo": "PUBLICACI\u00d3N DE LA MEMORIA ANUAL DE LA SOCIEDAD: AGROINDUSTRIAS LOCHMANN S.A.", "resumen": "PUBLICACI\u00d3N DE LA MEMORIA ANUAL DE LA SOCIEDAD: AGROINDUSTRIAS LOCHMANN S.A. DE LA GESTI\u00d3N: 2015", "fechaPublicacion": "2017-08-31T04:00:00.000Z", "empresa": {"matricula": "1024705020", "matriculaAnterior": "00013906", "razonSocial": "AGROINDUSTRIAS LOCHMANN S.A."}, "fechaPublicacionFormato": "2017/08/31"}, {"id": "49658", "codigo": "PUBN9BI02265", "titulo": "DISOLUCI\u00d3N Y LIQUIDACI\u00d3N DE SOCIEDAD COMERCIAL", "resumen": "DISOLUCION, LIQUIDACION DE SOCIEDAD COMERCIAL Y CONSIGUIENTE CANCELACION DE MATRICULA DE COMERCIO", "fechaPublicacion": "2017-08-31T04:00:00.000Z", "empresa": {"matricula": null, "matriculaAnterior": "00360473", "razonSocial": "IMPORTADORA SAN PABLO  S.R.L."}, "fechaPublicacionFormato": "2017/08/31"}, {"id": "49659", "codigo": "PUBS3I402264", "titulo": "PROYECTO DE DISTRIBUCI\u00d3N DE PATRIMONIO: IMPORTADORA SAN PABLO  S.R.L.", "resumen": "PROYECTO DE DISTRIBUCI\u00d3N DE PATRIMONIO", "fechaPublicacion": "2017-08-31T04:00:00.000Z", "empresa": {"matricula": null, "matriculaAnterior": "00360473", "razonSocial": "IMPORTADORA SAN PABLO  S.R.L."}, "fechaPublicacionFormato": "2017/08/31"}, {"id": "49660", "codigo": "PUBZU5202282", "titulo": "DISOLUCI\u00d3N Y LIQUIDACI\u00d3N DE SOCIEDAD COMERCIAL", "resumen": "DISOLUCION, LIQUIDACION DE SOCIEDAD COMERCIAL Y CONSIGUIENTE CANCELACION DE MATRICULA DE COMERCIO", "fechaPublicacion": "2017-08-31T04:00:00.000Z", "empresa": {"matricula": null, "matriculaAnterior": "00360485", "razonSocial": "IMPORTADORA VILLA COPACABANA S.R.L."}, "fechaPublicacionFormato": "2017/08/31"}, {"id": "49661", "codigo": "PUB1WU802270", "titulo": "PROYECTO DE DISTRIBUCI\u00d3N DE PATRIMONIO: IMPORTADORA VILLA COPACABANA S.R.L.", "resumen": "PROYECTO DE DISTRIBUCI\u00d3N DE PATRIMONIO", "fechaPublicacion": "2017-08-31T04:00:00.000Z", "empresa": {"matricula": null, "matriculaAnterior": "00360485", "razonSocial": "IMPORTADORA VILLA COPACABANA S.R.L."}, "fechaPublicacionFormato": "2017/08/31"}, {"id": "27127", "codigo": "PUBX77M02260", "titulo": "MODIFICACI\u00d3N, ACLARACI\u00d3N Y/O COMPLEMENTACI\u00d3N DE LA CONSTITUCI\u00d3N DE SOCIEDAD COMERCIAL", "resumen": "ESCRITURA PUBLICA SOBRE MODIFICACION AL DOMICILIO DE LA SOCIEDAD.", "fechaPublicacion": "2017-08-31T04:00:00.000Z", "empresa": {"matricula": "196256026", "matriculaAnterior": "00197972", "razonSocial": "PROSER S.R.L."}, "fechaPublicacionFormato": "2017/08/31"}, {"id": "49729", "codigo": "PUBEYZ302234", "titulo": "MODIFICACI\u00d3N, ACLARACI\u00d3N Y/O COMPLEMENTACI\u00d3N DE LA CONSTITUCI\u00d3N DE SOCIEDAD COMERCIAL", "resumen": "MODIFICACION A LA CONSTITUCION POR CAMBIO DE DENOMINACION SOCIAL, TRANSFERENCIA DE CUOTAS DE CAPITAL Y MODIFICACION AL OBJETO.", "fechaPublicacion": "2017-08-31T04:00:00.000Z", "empresa": {"matricula": "328728022", "matriculaAnterior": "00360686", "razonSocial": "GCC ARCHITECTURAL & ENGINEERING SOLUTIONS S.R.L."}, "fechaPublicacionFormato": "2017/08/31"}, {"id": "43112", "codigo": "PUBVYZI02286", "titulo": "TRANSFERENCIA DE CUOTAS DE CAPITAL", "resumen": "ESCRITURA PUBLICA DE TRANSFERENCIA DE CUOTAS DE CAPITAL Y CONSIGUIENTE MODIFICACION DE LA ESCRITURA DE CONSTITUCION.", "fechaPublicacion": "2017-08-31T04:00:00.000Z", "empresa": {"matricula": "304292027", "matriculaAnterior": "00337272", "razonSocial": "CADLAB S.R.L."}, "fechaPublicacionFormato": "2017/08/31"}, {"id": "6903", "codigo": "PUBDJRW02272", "titulo": "PUBLICACI\u00d3N DE LA MEMORIA ANUAL DE LA SOCIEDAD: EMPRESA DE ENVASES PAPELES Y CARTONES S.A. EMPACAR S.A.", "resumen": "PUBLICACI\u00d3N DE LA MEMORIA ANUAL DE LA SOCIEDAD: EMPRESA DE ENVASES PAPELES Y CARTONES S.A. EMPACAR S.A. DE LA GESTI\u00d3N: 2016", "fechaPublicacion": "2017-08-31T04:00:00.000Z", "empresa": {"matricula": "1028123025", "matriculaAnterior": "00013527", "razonSocial": "EMPRESA DE ENVASES PAPELES Y CARTONES S.A. EMPACAR S.A."}, "fechaPublicacionFormato": "2017/08/31"}, {"id": "17755", "codigo": "PUBER8102246", "titulo": "PUBLICACI\u00d3N DE LA MEMORIA ANUAL DE LA SOCIEDAD: CENTRO DE INVERSIONES TURISTICAS S.A.", "resumen": "PUBLICACI\u00d3N DE LA MEMORIA ANUAL DE LA SOCIEDAD: CENTRO DE INVERSIONES TURISTICAS S.A. DE LA GESTI\u00d3N: 2016", "fechaPublicacion": "2017-08-31T04:00:00.000Z", "empresa": {"matricula": "159218022", "matriculaAnterior": "00142428", "razonSocial": "CENTRO DE INVERSIONES TURISTICAS S.A."}, "fechaPublicacionFormato": "2017/08/31"}, {"id": "54208", "codigo": "PUBW63G02257", "titulo": "CONSTITUCI\u00d3N DE SOCIEDAD COMERCIAL S.R.L. SOCIEDAD COLECTIVA O SOCIEDAD EN COMANDITA SIMPLE", "resumen": "TESTIMONIO DE CONSTITUCION DE SOCIEDAD COMERCIAL", "fechaPublicacion": "2017-08-31T04:00:00.000Z", "empresa": {"matricula": "343214020", "matriculaAnterior": "00374104", "razonSocial": "SERVIPRO CONSULTING S.R.L."}, "fechaPublicacionFormato": "2017/08/31"}, {"id": "54220", "codigo": "PUBL0T202269", "titulo": "CONSTITUCI\u00d3N DE SOCIEDAD COMERCIAL S.R.L. SOCIEDAD COLECTIVA O SOCIEDAD EN COMANDITA SIMPLE", "resumen": "TESTIMONIO DE CONSTITUCION DE SOCIEDAD  DE RESPONSABILIDAD LIMITADA", "fechaPublicacion": "2017-08-31T04:00:00.000Z", "empresa": {"matricula": "337784027", "matriculaAnterior": "00374127", "razonSocial": "DRINKS FRANCHISE S.R.L."}, "fechaPublicacionFormato": "2017/08/31"}, {"id": "54222", "codigo": "PUBRCVB02276", "titulo": "CONSTITUCI\u00d3N DE SOCIEDAD COMERCIAL S.R.L. SOCIEDAD COLECTIVA O SOCIEDAD EN COMANDITA SIMPLE", "resumen": "TESTIMONIO DE CONSTITUCION DE SOCIEDAD DE RESPONSABILIDAD LIMITADA", "fechaPublicacion": "2017-08-31T04:00:00.000Z", "empresa": {"matricula": "343338021", "matriculaAnterior": "00374133", "razonSocial": "GLOBAL RAMOS COMPANY S.R.L."}, "fechaPublicacionFormato": "2017/08/31"}, {"id": "54223", "codigo": "PUBRYIU02283", "titulo": "CONSTITUCI\u00d3N DE SOCIEDAD COMERCIAL S.R.L. SOCIEDAD COLECTIVA O SOCIEDAD EN COMANDITA SIMPLE", "resumen": "TESTIMONIO DE CONSTITUCION DE SOCIEDAD DE RESPONSABILIDAD LIMITADA", "fechaPublicacion": "2017-08-31T04:00:00.000Z", "empresa": {"matricula": "347195028", "matriculaAnterior": "00374136", "razonSocial": "IBARO IMPORTACIONES S.R.L."}, "fechaPublicacionFormato": "2017/08/31"}, {"id": "330", "codigo": "PUB4WC002281", "titulo": "MODIFICACI\u00d3N, ACLARACI\u00d3N Y/O COMPLEMENTACI\u00d3N DE LA CONSTITUCI\u00d3N DE SOCIEDAD COMERCIAL", "resumen": "ESCRITURA PUBLICA DE CAMBIO DE DOMICILIO Y CONSIGUIENTE MODIFICACION AL TESTIMONIO DE CONSTITUCION", "fechaPublicacion": "2017-08-31T04:00:00.000Z", "empresa": {"matricula": "169134028", "matriculaAnterior": "00004825", "razonSocial": "PERSIALUMINIO S.R.L."}, "fechaPublicacionFormato": "2017/08/31"}, {"id": "33541", "codigo": "PUB5VSJ02245", "titulo": "TRANSFERENCIA DE CUOTAS DE CAPITAL", "resumen": "ESCRITURA P\u00daBLICA DE TRANSFERENCIA DE CUOTAS DE CAPITAL, CAMBIO DE DOMICILIO Y CONSIGUIENTE MODIFICACI\u00d3N DE ESCRITURA DE CONSTITUCI\u00d3N.", "fechaPublicacion": "2017-08-31T04:00:00.000Z", "empresa": {"matricula": "250524020", "matriculaAnterior": "00267391", "razonSocial": "EMPRESA MINERA \"RIGITH SOCIEDAD DE RESPONSABILIDAD LIMITADA\""}, "fechaPublicacionFormato": "2017/08/31"}, {"id": "40907", "codigo": "PUBNKUS02288", "titulo": "DISOLUCI\u00d3N Y LIQUIDACI\u00d3N DE SOCIEDAD COMERCIAL", "resumen": "DISOLUCION, LIQUIDACION DE SOCIEDAD COMERCIAL Y CONSIGUIENTE CANCELACION DE MATRICULA DE COMERCIO", "fechaPublicacion": "2017-08-31T04:00:00.000Z", "empresa": {"matricula": null, "matriculaAnterior": "00328620", "razonSocial": "COR-VIAL BOLIVIA S.R.L."}, "fechaPublicacionFormato": "2017/08/31"}, {"id": "16717", "codigo": "PUBOJ9602297", "titulo": "DISOLUCI\u00d3N Y LIQUIDACI\u00d3N DE SOCIEDAD COMERCIAL", "resumen": "LIQUIDACION DE SOCIEDAD COMERCIAL Y CONSIGUIENTE CANCELACION DE MATRICULA", "fechaPublicacion": "2017-08-31T04:00:00.000Z", "empresa": {"matricula": "167246026", "matriculaAnterior": "00136066", "razonSocial": "ARTESANIAS RELAVE LTDA"}, "fechaPublicacionFormato": "2017/08/31"}, {"id": "7988", "codigo": "PUB7CS702250", "titulo": "PUBLICACI\u00d3N DE LA MEMORIA ANUAL DE LA SOCIEDAD: AGROINDUSTRIAS LOCHMANN S.A.", "resumen": "PUBLICACI\u00d3N DE LA MEMORIA ANUAL DE LA SOCIEDAD: AGROINDUSTRIAS LOCHMANN S.A. DE LA GESTI\u00d3N: 2013", "fechaPublicacion": "2017-08-31T04:00:00.000Z", "empresa": {"matricula": "1024705020", "matriculaAnterior": "00013906", "razonSocial": "AGROINDUSTRIAS LOCHMANN S.A."}, "fechaPublicacionFormato": "2017/08/31"}, {"id": "2311", "codigo": "CNVBU4A00191", "titulo": "NOTIFICACION DE CAMBIO DE DIRECCION DE LA EMPRESA: VELARDE CONSTRUCCIONES S.R.L.", "resumen": "LA EMPRESA VELARDE CONSTRUCCIONES S.R.L. CON MATR\u00cdCULA DE COMERCIO: 00009119 ANUNCIA SU CAMBIO DE DIRECCI\u00d3N A: AV SANCHEZ BUSTAMANTE, N\u00b07977, EDIFICIO: CALACOTO BUSSINES CENTER, PISO: 2 , N\u00b0 DE OFICINA: 4  DE LA ZONA: CALACOTO", "fechaPublicacion": "2017-08-31T04:00:00.000Z", "empresa": {"matricula": "1007053026", "matriculaAnterior": "00009119", "razonSocial": "VELARDE CONSTRUCCIONES S.R.L."}, "fechaPublicacionFormato": "2017/08/31"}, {"id": "5708", "codigo": "PUB2MFX02278", "titulo": "PUBLICACI\u00d3N DE LA MEMORIA ANUAL DE LA SOCIEDAD: \"PETROBRAS BOLIVIA S.A.\"", "resumen": "PUBLICACI\u00d3N DE LA MEMORIA ANUAL DE LA SOCIEDAD: \"PETROBRAS BOLIVIA S.A.\" DE LA GESTI\u00d3N: 2016", "fechaPublicacion": "2017-08-31T04:00:00.000Z", "empresa": {"matricula": "1028173027", "matriculaAnterior": "00013273", "razonSocial": "\"PETROBRAS BOLIVIA S.A.\""}, "fechaPublicacionFormato": "2017/08/31"}, {"id": "7990", "codigo": "PUBZPEK02247", "titulo": "PUBLICACI\u00d3N DE LA MEMORIA ANUAL DE LA SOCIEDAD: AGROINDUSTRIAS LOCHMANN S.A.", "resumen": "PUBLICACI\u00d3N DE LA MEMORIA ANUAL DE LA SOCIEDAD: AGROINDUSTRIAS LOCHMANN S.A. DE LA GESTI\u00d3N: 2010", "fechaPublicacion": "2017-08-31T04:00:00.000Z", "empresa": {"matricula": "1024705020", "matriculaAnterior": "00013906", "razonSocial": "AGROINDUSTRIAS LOCHMANN S.A."}, "fechaPublicacionFormato": "2017/08/31"}, {"id": "21781", "codigo": "PUBAL4F02235", "titulo": "MODIFICACI\u00d3N, ACLARACI\u00d3N Y/O COMPLEMENTACI\u00d3N DE LA CONSTITUCI\u00d3N DE SOCIEDAD COMERCIAL", "resumen": "PRORROGA DEL PLAZO DE DURACION DE LA SOCIEDAD", "fechaPublicacion": "2017-08-31T04:00:00.000Z", "empresa": {"matricula": "170580025", "matriculaAnterior": "00166986", "razonSocial": "SOPORTE A LA CONSTRUCCION S.R.L."}, "fechaPublicacionFormato": "2017/08/31"}, {"id": "7991", "codigo": "PUBUHZX02249", "titulo": "PUBLICACI\u00d3N DE LA MEMORIA ANUAL DE LA SOCIEDAD: AGROINDUSTRIAS LOCHMANN S.A.", "resumen": "PUBLICACI\u00d3N DE LA MEMORIA ANUAL DE LA SOCIEDAD: AGROINDUSTRIAS LOCHMANN S.A. DE LA GESTI\u00d3N: 2012", "fechaPublicacion": "2017-08-31T04:00:00.000Z", "empresa": {"matricula": "1024705020", "matriculaAnterior": "00013906", "razonSocial": "AGROINDUSTRIAS LOCHMANN S.A."}, "fechaPublicacionFormato": "2017/08/31"}, {"id": "17011", "codigo": "PUBYE2M02230", "titulo": "MODIFICACI\u00d3N, ACLARACI\u00d3N Y/O COMPLEMENTACI\u00d3N DE LA CONSTITUCI\u00d3N DE SOCIEDAD COMERCIAL", "resumen": "TRANSFERENCIA DE CUOTAS DE CAPITAL INGRESO DE NUEVO SOCIO", "fechaPublicacion": "2017-08-31T04:00:00.000Z", "empresa": {"matricula": "155800022", "matriculaAnterior": "00137846", "razonSocial": "AMURRIO & ASOCIADOS, CONSULTORES S.R.L."}, "fechaPublicacionFormato": "2017/08/31"}, {"id": "29335", "codigo": "PUBJL2002300", "titulo": "DISOLUCI\u00d3N Y LIQUIDACI\u00d3N DE SOCIEDAD COMERCIAL", "resumen": "ESCRITURA PUBLICA DE DISOLUCION, LIQUIDACION DE SOCIEDAD DE RESPONSABILIDAD LIMITADA NO. 17/2013 DE FECHA 24/01/2013.", "fechaPublicacion": "2017-08-31T04:00:00.000Z", "empresa": {"matricula": "212628021", "matriculaAnterior": "00218237", "razonSocial": "\" CONSTRUCTORA Y CONSULTORA HERACLES S.R.L.\""}, "fechaPublicacionFormato": "2017/08/31"}, {"id": "16618", "codigo": "CNVZMI700176", "titulo": "NOTIFICACION DE CAMBIO DE DIRECCION DE LA EMPRESA: COMERCIALIZADORA EMASA BOLIVIA S.R.L.", "resumen": "LA EMPRESA COMERCIALIZADORA EMASA BOLIVIA S.R.L. CON MATR\u00cdCULA DE COMERCIO: 00135596 ANUNCIA SU CAMBIO DE DIRECCI\u00d3N A: AV. 4\u00ba ANILLO , N\u00b04200, UNIDAD VECINAL: 059, MZA.: 055, EDIFICIO: CENTRO EMPRESARIAL TORRE DUO, PISO: 12  DE LA ZONA: EQUIPETROL NORTE", "fechaPublicacion": "2017-08-31T04:00:00.000Z", "empresa": {"matricula": "153814024", "matriculaAnterior": "00135596", "razonSocial": "COMERCIALIZADORA EMASA BOLIVIA S.R.L."}, "fechaPublicacionFormato": "2017/08/31"}, {"id": "23177", "codigo": "PUB392102238", "titulo": "DISOLUCI\u00d3N Y LIQUIDACI\u00d3N DE SOCIEDAD COMERCIAL", "resumen": "ESCRITURA PUBLICA DE DISOLUCION, LIQUIDACION Y CONSIGUIENTE CANCELACION DE MATRICULA DE COMERCIO", "fechaPublicacion": "2017-08-31T04:00:00.000Z", "empresa": {"matricula": "182684026", "matriculaAnterior": "00175798", "razonSocial": "BRAKHACON S.R.L."}, "fechaPublicacionFormato": "2017/08/31"}, {"id": "12893", "codigo": "CNVWU9K00197", "titulo": "NOTIFICACION DE CAMBIO DE DIRECCION DE LA EMPRESA: SERVICIOS GENERALES \"SICOMETP\"", "resumen": "LA EMPRESA SERVICIOS GENERALES \"SICOMETP\" CON MATR\u00cdCULA DE COMERCIO: 00112390 ANUNCIA SU CAMBIO DE DIRECCI\u00d3N A: AV. NUEVA JERUSALEN, N\u00b02 A, UNIDAD VECINAL: 283, MZA.: 010  DE LA ZONA: B/ 12 DE OCTUBRE", "fechaPublicacion": "2017-08-31T04:00:00.000Z", "empresa": {"matricula": "6310839016", "matriculaAnterior": "00112390", "razonSocial": "PEDRO CASTRO CUELLAR"}, "fechaPublicacionFormato": "2017/08/31"}, {"id": "23178", "codigo": "PUB6G5Z02240", "titulo": "PROYECTO DE DISTRIBUCI\u00d3N DE PATRIMONIO: BRAKHACON S.R.L.", "resumen": "PROYECTO DE DISTRIBUCI\u00d3N DE PATRIMONIO", "fechaPublicacion": "2017-08-31T04:00:00.000Z", "empresa": {"matricula": "182684026", "matriculaAnterior": "00175798", "razonSocial": "BRAKHACON S.R.L."}, "fechaPublicacionFormato": "2017/08/31"}, {"id": "7992", "codigo": "PUBLDPZ02248", "titulo": "PUBLICACI\u00d3N DE LA MEMORIA ANUAL DE LA SOCIEDAD: AGROINDUSTRIAS LOCHMANN S.A.", "resumen": "PUBLICACI\u00d3N DE LA MEMORIA ANUAL DE LA SOCIEDAD: AGROINDUSTRIAS LOCHMANN S.A. DE LA GESTI\u00d3N: 2011", "fechaPublicacion": "2017-08-31T04:00:00.000Z", "empresa": {"matricula": "1024705020", "matriculaAnterior": "00013906", "razonSocial": "AGROINDUSTRIAS LOCHMANN S.A."}, "fechaPublicacionFormato": "2017/08/31"}, {"id": "1507", "codigo": "PUBK3ZT02292", "titulo": "MODIFICACI\u00d3N, ACLARACI\u00d3N Y/O COMPLEMENTACI\u00d3N DE LA CONSTITUCI\u00d3N DE SOCIEDAD COMERCIAL", "resumen": "ESCRITURA PUBLICA DE CAMBIO DE DOMICILIO Y CONSIGUIENTE MODIFICACION DE LA ESCRITURA DE CONSTITUCION.", "fechaPublicacion": "2017-08-31T04:00:00.000Z", "empresa": {"matricula": "1004253029", "matriculaAnterior": "00007860", "razonSocial": "EMPRESA CONSTRUCTORA SCKEMA S.R.L."}, "fechaPublicacionFormato": "2017/08/31"}, {"id": "39058", "codigo": "CNV16L200192", "titulo": "NOTIFICACION DE CAMBIO DE DIRECCION DE LA EMPRESA: XBOX HOLDINGS & ENTERPRISES INC. S.R.L.", "resumen": "LA EMPRESA XBOX HOLDINGS & ENTERPRISES INC. S.R.L. CON MATR\u00cdCULA DE COMERCIO: 00320390 ANUNCIA SU CAMBIO DE DIRECCI\u00d3N A: PANDO, N\u00b01270, EDIFICIO: HUPER MALL, PISO: 7 , N\u00b0 DE OFICINA: 10  DE LA ZONA: QUERU QUERU", "fechaPublicacion": "2017-08-31T04:00:00.000Z", "empresa": {"matricula": "296428021", "matriculaAnterior": "00320390", "razonSocial": "XBOX HOLDINGS & ENTERPRISES INC. S.R.L."}, "fechaPublicacionFormato": "2017/08/31"}, {"id": "21073", "codigo": "PUBJJF002268", "titulo": "DISOLUCI\u00d3N Y LIQUIDACI\u00d3N DE SOCIEDAD COMERCIAL", "resumen": "DISOLUCION, LIQUIDACION DE SOCIEDAD COMERCIAL Y CONSIGUIENTE CANCELACION DE MATRICULA DE COMERCIO", "fechaPublicacion": "2017-08-31T04:00:00.000Z", "empresa": {"matricula": "172978020", "matriculaAnterior": "00162717", "razonSocial": "CONSTRUCTORA CASTRO ROSERO PATERNINA S.R.L."}, "fechaPublicacionFormato": "2017/08/31"}, {"id": "21072", "codigo": "PUBWN9J02267", "titulo": "PROYECTO DE DISTRIBUCI\u00d3N DE PATRIMONIO: CONSTRUCTORA CASTRO ROSERO PATERNINA S.R.L.", "resumen": "PROYECTO DE DISTRIBUCI\u00d3N DE PATRIMONIO", "fechaPublicacion": "2017-08-31T04:00:00.000Z", "empresa": {"matricula": "172978020", "matriculaAnterior": "00162717", "razonSocial": "CONSTRUCTORA CASTRO ROSERO PATERNINA S.R.L."}, "fechaPublicacionFormato": "2017/08/31"}, {"id": "143", "codigo": "CNVZIW200199", "titulo": "NOTIFICACION DE CAMBIO DE DIRECCION DE LA EMPRESA: INGENIERIA Y TECNOLOGIA EN ESTRUCTURAS DE CONCRETO Y ACERO ITECA", "resumen": "LA EMPRESA INGENIERIA Y TECNOLOGIA EN ESTRUCTURAS DE CONCRETO Y ACERO ITECA CON MATR\u00cdCULA DE COMERCIO: 00001746 ANUNCIA SU CAMBIO DE DIRECCI\u00d3N A: CALLE EDUARDO CALDERON, N\u00b01268, UNIDAD VECINAL: PLAN 561  DE LA ZONA: CIUDAD SATELITE - EL ALTO", "fechaPublicacion": "2017-08-31T04:00:00.000Z", "empresa": {"matricula": "3476877014", "matriculaAnterior": "00001746", "razonSocial": "INGENIERIA Y TECNOLOGIA EN ESTRUCTURAS DE CONCRETO Y ACERO ITECA"}, "fechaPublicacionFormato": "2017/08/31"}, {"id": "12395", "codigo": "CNVCCLJ00193", "titulo": "NOTIFICACION DE CAMBIO DE DIRECCION DE LA EMPRESA: CONSTRUCTORA Y SERVICIOS URQUIZO SRL", "resumen": "LA EMPRESA CONSTRUCTORA Y SERVICIOS URQUIZO SRL CON MATR\u00cdCULA DE COMERCIO: 00109364 ANUNCIA SU CAMBIO DE DIRECCI\u00d3N A: PLAZA BADEN POWELL, N\u00b095  DE LA ZONA: MIRAFLORES", "fechaPublicacion": "2017-08-31T04:00:00.000Z", "empresa": {"matricula": "1029421025", "matriculaAnterior": "00109364", "razonSocial": "CONSTRUCTORA Y SERVICIOS URQUIZO SRL"}, "fechaPublicacionFormato": "2017/08/31"}, {"id": "37093", "codigo": "CNV09PS00188", "titulo": "NOTIFICACION DE CAMBIO DE DIRECCION DE LA EMPRESA: JUAN CARLOS MARCANI SEJAS", "resumen": "LA EMPRESA JUAN CARLOS MARCANI SEJAS CON MATR\u00cdCULA DE COMERCIO: 00304552 ANUNCIA SU CAMBIO DE DIRECCI\u00d3N A: AVENIDA PEDRO BLANCO, N\u00b0247, EDIFICIO: PUERTO BALLARTA, PISO: PLANTA BAJA , N\u00b0 DE OFICINA: 3  DE LA ZONA: QUERU QUERU", "fechaPublicacion": "2017-08-31T04:00:00.000Z", "empresa": {"matricula": "4477015011", "matriculaAnterior": "00304552", "razonSocial": "JUAN CARLOS MARCANI SEJAS"}, "fechaPublicacionFormato": "2017/08/31"}, {"id": "39819", "codigo": "CNV4NBC00186", "titulo": "NOTIFICACION DE CAMBIO DE DIRECCION DE LA EMPRESA: MOVICORP S.R.L.", "resumen": "LA EMPRESA MOVICORP S.R.L. CON MATR\u00cdCULA DE COMERCIO: 00323597 ANUNCIA SU CAMBIO DE DIRECCI\u00d3N A: C/MANANTIAL, N\u00b0S/N, MZA.: 0004  DE LA ZONA: B/ 4 DE NOVIEMBRE", "fechaPublicacion": "2017-08-31T04:00:00.000Z", "empresa": {"matricula": "297050021", "matriculaAnterior": "00323597", "razonSocial": "MOVICORP S.R.L."}, "fechaPublicacionFormato": "2017/08/31"}]}}