{"finalizado": true, "mensaje": "\u00a1Registro(s) obtenido(s) con \u00e9xito!", "datos": {"total": 103525, "filas": [{"id": "81247", "codigo": "PUB4LEY45873", "titulo": "CONSTITUCI\u00d3N DE SOCIEDAD COMERCIAL S.R.L. SOCIEDAD COLECTIVA O SOCIEDAD EN COMANDITA SIMPLE", "resumen": "TESTIMONIO DE CONSTITUCION DE SOCIEDAD DE RESPONSABILIDAD LIMITADA", "fechaPublicacion": "2021-07-09T04:00:00.000Z", "empresa": {"matricula": "409275022", "matriculaAnterior": "00449960", "razonSocial": "BIOSERV BIOMEDICINA MEDICA\u00a0 DE SERVICIOS BOLIVIA S.R.L."}, "fechaPublicacionFormato": "2021/07/09"}, {"id": "81251", "codigo": "PUBL1KU45876", "titulo": "CONSTITUCI\u00d3N DE SOCIEDAD COMERCIAL S.R.L. SOCIEDAD COLECTIVA O SOCIEDAD EN COMANDITA SIMPLE", "resumen": "CONSTITUCION DE SOCIEDAD DE RESPONSABILIDAD LIMITADA", "fechaPublicacion": "2021-07-09T04:00:00.000Z", "empresa": {"matricula": "408948025", "matriculaAnterior": "00449966", "razonSocial": "NANOFERT BOLIVIA S.R.L."}, "fechaPublicacionFormato": "2021/07/09"}, {"id": "9959", "codigo": "PUBB73M45802", "titulo": "PUBLICACI\u00d3N DE LA MEMORIA ANUAL DE LA SOCIEDAD: ENTIDAD DE DEPOSITO DE VALORES DE BOLIVIA S.A.  EDV", "resumen": "PUBLICACI\u00d3N DE LA MEMORIA ANUAL DE LA SOCIEDAD: ENTIDAD DE DEPOSITO DE VALORES DE BOLIVIA S.A.  EDV DE LA GESTI\u00d3N: 2020", "fechaPublicacion": "2021-07-09T04:00:00.000Z", "empresa": {"matricula": "1020219028", "matriculaAnterior": "00048379", "razonSocial": "ENTIDAD DE DEPOSITO DE VALORES DE BOLIVIA S.A.  EDV"}, "fechaPublicacionFormato": "2021/07/09"}, {"id": "81257", "codigo": "PUBZWH145887", "titulo": "CONSTITUCI\u00d3N DE SOCIEDAD COMERCIAL S.R.L. SOCIEDAD COLECTIVA O SOCIEDAD EN COMANDITA SIMPLE", "resumen": "TESTIMONIO DE CONSTITUCION DE SOCIEDAD COMERCIAL", "fechaPublicacion": "2021-07-09T04:00:00.000Z", "empresa": {"matricula": "410409029", "matriculaAnterior": "00449989", "razonSocial": "DGSTRANSPORT S.R.L."}, "fechaPublicacionFormato": "2021/07/09"}, {"id": "81260", "codigo": "PUB1RDB45891", "titulo": "CONSTITUCI\u00d3N DE SOCIEDAD COMERCIAL S.R.L. SOCIEDAD COLECTIVA O SOCIEDAD EN COMANDITA SIMPLE", "resumen": "TESTIMONIO DE CONSTITUCION DE SOCIEDAD COMERCIAL", "fechaPublicacion": "2021-07-09T04:00:00.000Z", "empresa": {"matricula": "408958026", "matriculaAnterior": "00449996", "razonSocial": "AGROBARRIENTOS S.R.L."}, "fechaPublicacionFormato": "2021/07/09"}, {"id": "81261", "codigo": "PUBZFLZ45892", "titulo": "CONSTITUCI\u00d3N DE SOCIEDAD COMERCIAL S.R.L. SOCIEDAD COLECTIVA O SOCIEDAD EN COMANDITA SIMPLE", "resumen": "TESTIMONIO DE CONSTITUCION DE SOCIEDAD DE RESPONSABILIDAD LIMITADA", "fechaPublicacion": "2021-07-09T04:00:00.000Z", "empresa": {"matricula": "409844020", "matriculaAnterior": "00450000", "razonSocial": "EMPRESA DE TRANSPORTE INTERNACIONAL ORALBA S.R.L."}, "fechaPublicacionFormato": "2021/07/09"}, {"id": "81262", "codigo": "PUBCTSW45894", "titulo": "CONSTITUCI\u00d3N DE SOCIEDAD COMERCIAL S.R.L. SOCIEDAD COLECTIVA O SOCIEDAD EN COMANDITA SIMPLE", "resumen": "TESTIMONIO DE CONSTITUCION DE SOCIEDAD DE RESPONSABILIDAD LIMITADA", "fechaPublicacion": "2021-07-09T04:00:00.000Z", "empresa": {"matricula": "408884020", "matriculaAnterior": "00450003", "razonSocial": "EMPRESA MINERA KELDERSON S.R.L."}, "fechaPublicacionFormato": "2021/07/09"}, {"id": "25261", "codigo": "CNV2R5734999", "titulo": "NOTIFICACI\u00d3N DE CAMBIO DE DIRECCI\u00d3N DE LA EMPRESA:", "resumen": "LA EMPRESA SANVITUR CON MATR\u00cdCULA DE COMERCIO: 00187506        ANUNCIA SU CAMBIO DE DIRECCI\u00d3N  A: CALLE ANTONIO QUIJARRO,         N\u00b0: 987, ENTRE CALLES: AVENIDA BAPTISTA Y CALLE JUAN GRANIER, UNIDAD VECINAL: S/N, MZA.: S/N, EDIFICIO: SN, PISO: SN, N\u00b0 DE OFICINA: SN DE LA ZONA: 14 DE SEPTIEMBRE", "fechaPublicacion": "2021-07-09T04:00:00.000Z", "empresa": {"matricula": "4880616014", "matriculaAnterior": "00187506", "razonSocial": "SANVITUR"}, "fechaPublicacionFormato": "2021/07/09"}, {"id": "17158", "codigo": "CNVLJGR34995", "titulo": "NOTIFICACI\u00d3N DE CAMBIO DE DIRECCI\u00d3N DE LA EMPRESA:", "resumen": "LA EMPRESA A3TEK S.R.L. CON MATR\u00cdCULA DE COMERCIO: 00138663        ANUNCIA SU CAMBIO DE DIRECCI\u00d3N DE SU SUCURSAL {SUCURSAL_NOMBRE} A: PASAJES VILLEGAS,         N\u00b0: 1218, ENTRE CALLES: A MEDIA CUADRA DE LA CALLE CAMPOS, UNIDAD VECINAL: S/N, MZA.: S/N, EDIFICIO: S/N, PISO: S/N, N\u00b0 DE OFICINA: 2 DE LA ZONA: SOPOCACHI BAJO", "fechaPublicacion": "2021-07-09T04:00:00.000Z", "empresa": {"matricula": "156368028", "matriculaAnterior": "00138663", "razonSocial": "A3TEK S.R.L."}, "fechaPublicacionFormato": "2021/07/09"}, {"id": "77275", "codigo": "PUB4K6145897", "titulo": "TRANSFERENCIA DE CUOTAS DE CAPITAL", "resumen": "ESCRITURA PUBLICA DE TRANSFERENCIA DE CUOTAS DE CAPITAL", "fechaPublicacion": "2021-07-09T04:00:00.000Z", "empresa": {"matricula": "396612024", "matriculaAnterior": "00437749", "razonSocial": "CONSTRUCTORA CONELSUD S.R.L."}, "fechaPublicacionFormato": "2021/07/09"}, {"id": "13249", "codigo": "CNVA92I34998", "titulo": "NOTIFICACI\u00d3N DE CAMBIO DE DIRECCI\u00d3N DE LA EMPRESA:", "resumen": "LA EMPRESA ARACUAIYA - YEROVIA JARDIN DE INFANTES CON MATR\u00cdCULA DE COMERCIO: 00115042        ANUNCIA SU CAMBIO DE DIRECCI\u00d3N  A: CALLE CABO GUMERCINDO,         N\u00b0: 3130, ENTRE CALLES: ENTRE SANTOS DUMONT Y RADIAL 13 , ENTRE 3ER Y 4TO ANILLO, AL LADO DE PROSALUD LA MORITA, UNIDAD VECINAL: 48, MZA.: 12, EDIFICIO: S/N, PISO: S/N, N\u00b0 DE OFICINA: S/N DE LA ZONA: BARRIO LA MORITA", "fechaPublicacion": "2021-07-09T04:00:00.000Z", "empresa": {"matricula": "3220063018", "matriculaAnterior": "00115042", "razonSocial": "ARACUAIYA CORPORACI\u00d3N EDUCATIVA"}, "fechaPublicacionFormato": "2021/07/09"}, {"id": "21408", "codigo": "CNVS0GX34998", "titulo": "NOTIFICACI\u00d3N DE CAMBIO DE DIRECCI\u00d3N DE LA EMPRESA:", "resumen": "LA EMPRESA GESTION Y SOPORTE DE PROYECTOS JESUS DEL GRAN PODER S.A. CON MATR\u00cdCULA DE COMERCIO: 00164295        ANUNCIA SU CAMBIO DE DIRECCI\u00d3N DE SU SUCURSAL {SUCURSAL_NOMBRE} A: PAMPAJASI CALLE E N\u00b0 50,         N\u00b0: 50, ENTRE CALLES: ESQUINA AVENIDA CIRCUNVALACION, UNIDAD VECINAL: S/N, MZA.: S/N, EDIFICIO: S/N, PISO: 1, N\u00b0 DE OFICINA: 1 DE LA ZONA: PAMPAHASI", "fechaPublicacion": "2021-07-09T04:00:00.000Z", "empresa": {"matricula": "173788022", "matriculaAnterior": "00164295", "razonSocial": "GESTION Y SOPORTE DE PROYECTOS JESUS DEL GRAN PODER S.A."}, "fechaPublicacionFormato": "2021/07/09"}, {"id": "78643", "codigo": "CNVUQ2R34994", "titulo": "NOTIFICACI\u00d3N DE CAMBIO DE DIRECCI\u00d3N DE LA EMPRESA:", "resumen": "LA EMPRESA DARNEL BOLIVIA S.R.L. CON MATR\u00cdCULA DE COMERCIO: 00441917        ANUNCIA SU CAMBIO DE DIRECCI\u00d3N  A: AV.  LAS VIOLETAS,         N\u00b0: 1800, ENTRE CALLES: 3ER Y 4TO ANILLO A UNA CUADRA DEL 4TO ANILLO Y A MEDIA DE LA AVENIDA, UNIDAD VECINAL: 58, MZA.: 28, EDIFICIO: TACUARAL II, PISO: 4, N\u00b0 DE OFICINA: 403 DE LA ZONA: EQUIPETROL NORTE", "fechaPublicacion": "2021-07-09T04:00:00.000Z", "empresa": {"matricula": "402823021", "matriculaAnterior": "00441917", "razonSocial": "DARNEL BOLIVIA S.R.L."}, "fechaPublicacionFormato": "2021/07/09"}, {"id": "72142", "codigo": "CNVP0CQ34997", "titulo": "NOTIFICACI\u00d3N DE CAMBIO DE DIRECCI\u00d3N DE LA EMPRESA:", "resumen": "LA EMPRESA GRUPOANSO S.R.L. CON MATR\u00cdCULA DE COMERCIO: 00422924        ANUNCIA SU CAMBIO DE DIRECCI\u00d3N  A: AVENIDA: 3ER ANILLO INTERNO ESQUINA AVENIDA BUSCH,         N\u00b0: S/N, ENTRE CALLES: ENTRE EL 3ER ANILLO INTERNO Y AVENIDA BUSCH, UNIDAD VECINAL: 0033-, MZA.: 0045-, EDIFICIO: PATIO DESING LIFESTYLE CENTER, PISO: 2, N\u00b0 DE OFICINA: 206 DE LA ZONA: FAREMAFU", "fechaPublicacion": "2021-07-09T04:00:00.000Z", "empresa": {"matricula": "386830028", "matriculaAnterior": "00422924", "razonSocial": "GRUPOANSO S.R.L."}, "fechaPublicacionFormato": "2021/07/09"}, {"id": "81248", "codigo": "PUB6PCD45874", "titulo": "CONSTITUCI\u00d3N DE SOCIEDAD COMERCIAL S.A., SOCIEDAD EN COMANDITA POR ACCIONES CONSTITUIDAS POR ACTO \u00daNICO, POR SUSCRIPCI\u00d3N P\u00daBLICA DE ACCIONES O CONSTITUCI\u00d3N DE SOCIEDAD DE ECONOM\u00cdA MIXTA", "resumen": "CONSTITUCION DE SOCIEDAD ANONIMA POR ACTO UNICO.", "fechaPublicacion": "2021-07-09T04:00:00.000Z", "empresa": {"matricula": "418949027", "matriculaAnterior": "00449962", "razonSocial": "PRODUCTORA H2 BOLIVIA SOCIEDAD AN\u00d3NIMA"}, "fechaPublicacionFormato": "2021/07/09"}, {"id": "79295", "codigo": "PUBE0S345889", "titulo": "MODIFICACI\u00d3N, ACLARACI\u00d3N Y/O COMPLEMENTACI\u00d3N DE LA CONSTITUCI\u00d3N DE SOCIEDAD COMERCIAL", "resumen": "PROTOCOLIZACION DE UNA MINUTA DE MODIFICACION DE ESCRITURA DE CONSTITUCION", "fechaPublicacion": "2021-07-09T04:00:00.000Z", "empresa": {"matricula": "409070022", "matriculaAnterior": "00443938", "razonSocial": "GUHAEN S.R.L."}, "fechaPublicacionFormato": "2021/07/09"}, {"id": "20336", "codigo": "PUBO04Y45878", "titulo": "MODIFICACI\u00d3N, ACLARACI\u00d3N Y/O COMPLEMENTACI\u00d3N DE LA CONSTITUCI\u00d3N DE SOCIEDAD COMERCIAL", "resumen": "MODIFICACION A LA CONSTITUCION POR AMPLIACION DEL OBJETO SOCIAL", "fechaPublicacion": "2021-07-09T04:00:00.000Z", "empresa": {"matricula": "170722021", "matriculaAnterior": "00158487", "razonSocial": "COMERCIAL IMPORTADORA ALEA S.R.L."}, "fechaPublicacionFormato": "2021/07/09"}, {"id": "31860", "codigo": "PUBK99E45884", "titulo": "TRANSFERENCIA DE CUOTAS DE CAPITAL", "resumen": "ESCRITURA DE TRANSFERENCIA DE CUOTAS DE CAPITAL", "fechaPublicacion": "2021-07-09T04:00:00.000Z", "empresa": {"matricula": "231822025", "matriculaAnterior": "00244735", "razonSocial": "FRANECAR S.R.L."}, "fechaPublicacionFormato": "2021/07/09"}, {"id": "80034", "codigo": "CNVYRHW34999", "titulo": "NOTIFICACI\u00d3N DE CAMBIO DE DIRECCI\u00d3N DE LA EMPRESA: EMPRESA DE TRANSPORTE NACIONAL E INTERNACIONAL ANUBIS S.R.L.", "resumen": "LA EMPRESA EMPRESA DE TRANSPORTE NACIONAL E INTERNACIONAL ANUBIS S.R.L. CON MATR\u00cdCULA DE COMERCIO: 00446028 ANUNCIA SU CAMBIO DE DIRECCI\u00d3N A: CALLE PEATONAL 5, N\u00b0 5212  DE LA ZONA: RIO SECO", "fechaPublicacion": "2021-07-09T04:00:00.000Z", "empresa": {"matricula": "405825022", "matriculaAnterior": "00446028", "razonSocial": "EMPRESA DE TRANSPORTE NACIONAL E INTERNACIONAL ANUBIS S.R.L."}, "fechaPublicacionFormato": "2021/07/09"}, {"id": "31073", "codigo": "PUB2SRV45852", "titulo": "TRANSFERENCIA DE CUOTAS DE CAPITAL", "resumen": "TRANSFERENCIA DE CUOTAS DE CAPITAL Y CONSIGUIENTE MODIFICACION A LA CONSTITUCION", "fechaPublicacion": "2021-07-09T04:00:00.000Z", "empresa": {"matricula": "229720020", "matriculaAnterior": "00234776", "razonSocial": "MICRAS S.R.L."}, "fechaPublicacionFormato": "2021/07/09"}, {"id": "9160", "codigo": "PUBILP145855", "titulo": "MODIFICACI\u00d3N, ACLARACI\u00d3N Y/O COMPLEMENTACI\u00d3N DE LA CONSTITUCI\u00d3N DE SOCIEDAD COMERCIAL", "resumen": "PRORROGA DEL PLAZO DE DURACION Y CONSIGUIENTE MODIFICACION A LA CONSTITUCION", "fechaPublicacion": "2021-07-09T04:00:00.000Z", "empresa": {"matricula": "127335026", "matriculaAnterior": "00045448", "razonSocial": "EMPRESA DE TRANSPORTE SAN JUAN S.R.L."}, "fechaPublicacionFormato": "2021/07/09"}, {"id": "80940", "codigo": "PUBFW2N45882", "titulo": "TRANSFORMACI\u00d3N", "resumen": "ESCRITURA PUBLICA DE TRANSFORMACION DE EMPRESA UNIPERSONAL EN SOCIEDAD DE RESPONSABILIDAD LIMITADA", "fechaPublicacion": "2021-07-09T04:00:00.000Z", "empresa": {"matricula": "409069021", "matriculaAnterior": "00448955", "razonSocial": "YOUTHS BUILDINGS S.R.L."}, "fechaPublicacionFormato": "2021/07/09"}, {"id": "8940", "codigo": "PUBVN5445886", "titulo": "MODIFICACI\u00d3N, ACLARACI\u00d3N Y/O COMPLEMENTACI\u00d3N DE LA CONSTITUCI\u00d3N DE SOCIEDAD COMERCIAL", "resumen": "ESCRITURA PUBLICA DE REDUCCION DE APORTES DE SOCIO, AUMENTO DE CAPITAL, REDUCCION DE CAPITAL POR ABSORCION DE PERDIDAS Y CONSIGUIENTE MODIFICACION DE LA ESCRITURA CONSTITUTIVA DE LA SOCIEDAD.", "fechaPublicacion": "2021-07-09T04:00:00.000Z", "empresa": {"matricula": "1014269028", "matriculaAnterior": "00042534", "razonSocial": "COMPA\u00d1IA INDUSTRIAL MADERERA LTDA."}, "fechaPublicacionFormato": "2021/07/09"}, {"id": "42469", "codigo": "PUBLGEL45856", "titulo": "TRANSFERENCIA DE CUOTAS DE CAPITAL", "resumen": "TRANSFERENCIA DE CUOTAS DE CAPITAL POR RETIRO DE SOCIO", "fechaPublicacion": "2021-07-09T04:00:00.000Z", "empresa": {"matricula": "302024028", "matriculaAnterior": "00334903", "razonSocial": "NEW GROUP CONSULTING & CONSTRUCTIONS S.R.L."}, "fechaPublicacionFormato": "2021/07/09"}, {"id": "2908", "codigo": "PUB4KSK45895", "titulo": "MODIFICACI\u00d3N, ACLARACI\u00d3N Y/O COMPLEMENTACI\u00d3N DE LA CONSTITUCI\u00d3N DE SOCIEDAD COMERCIAL", "resumen": "ESCRITURA PUBLICA DE MODIFICACION  DE OBJETO.", "fechaPublicacion": "2021-07-09T04:00:00.000Z", "empresa": {"matricula": "1006109026", "matriculaAnterior": "00010438", "razonSocial": "GUMMYPLAS S.R.L."}, "fechaPublicacionFormato": "2021/07/09"}, {"id": "81265", "codigo": "PUB8JQK45899", "titulo": "CONSTITUCI\u00d3N DE SOCIEDAD COMERCIAL S.R.L. SOCIEDAD COLECTIVA O SOCIEDAD EN COMANDITA SIMPLE", "resumen": "TESTIMONIO DE CONSTITUCION DE SOCIEDAD DE RESPONSABILIDAD LIMITADA", "fechaPublicacion": "2021-07-09T04:00:00.000Z", "empresa": {"matricula": "409470025", "matriculaAnterior": "00450030", "razonSocial": "PICKPACKWAREHOUSE BOLIVIA S.R.L."}, "fechaPublicacionFormato": "2021/07/09"}, {"id": "49786", "codigo": "CNVGKPG35000", "titulo": "NOTIFICACI\u00d3N DE CAMBIO DE DIRECCI\u00d3N DE LA EMPRESA:", "resumen": "LA EMPRESA TECNOLOGIA Y COMUNICACION \"TECNOCOM LTDA\" CON MATR\u00cdCULA DE COMERCIO: 00360888        ANUNCIA SU CAMBIO DE DIRECCI\u00d3N  A: CALLE CAPITAN TELMO ROMERO,         N\u00b0: 2, ENTRE CALLES: SGTO. ZOLIO SAAVEDRA Y PROSPERO PARADA, UNIDAD VECINAL: 0048, MZA.: 0051, EDIFICIO: S/N, PISO: S/N, N\u00b0 DE OFICINA: S/N DE LA ZONA: BARRIO LA MORITA", "fechaPublicacion": "2021-07-09T04:00:00.000Z", "empresa": {"matricula": "328840026", "matriculaAnterior": "00360888", "razonSocial": "TECNOLOGIA Y COMUNICACION \"TECNOCOM LTDA\""}, "fechaPublicacionFormato": "2021/07/09"}, {"id": "39668", "codigo": "PUBOTM545853", "titulo": "TRANSFERENCIA DE CUOTAS DE CAPITAL", "resumen": "TRANSFERENCIA DE CUOTAS DE CAPITAL", "fechaPublicacion": "2021-07-09T04:00:00.000Z", "empresa": {"matricula": "293288027", "matriculaAnterior": "00322757", "razonSocial": "DATA RED S.R.L."}, "fechaPublicacionFormato": "2021/07/09"}, {"id": "64337", "codigo": "CNVR14534999", "titulo": "NOTIFICACI\u00d3N DE CAMBIO DE DIRECCI\u00d3N DE LA EMPRESA:", "resumen": "LA EMPRESA LIVINGROOM S.R.L. CON MATR\u00cdCULA DE COMERCIO: 00403262        ANUNCIA SU CAMBIO DE DIRECCI\u00d3N DE SU SUCURSAL {SUCURSAL_NOMBRE} A: AV. LA SALLE (CANAL ISUTO) ENTRE 2DO Y 3ER ANILLO ESQ. CALLE FRANZ TAMAYO N\u00b06,         N\u00b0: 6, ENTRE CALLES: CANAL ISUTO ENTRE 2DO Y 3ER ANILLO ESQ. CALLE FRANZ TAMAYO N\u00b06, UNIDAD VECINAL: S/N, MZA.: 001, EDIFICIO: S/N, PISO: S/N, N\u00b0 DE OFICINA: S/N DE LA ZONA: EQUIPETROL", "fechaPublicacion": "2021-07-09T04:00:00.000Z", "empresa": {"matricula": "370776024", "matriculaAnterior": "00403262", "razonSocial": "LIVINGROOM S.R.L."}, "fechaPublicacionFormato": "2021/07/09"}, {"id": "74362", "codigo": "CNVYGXS34996", "titulo": "NOTIFICACI\u00d3N DE CAMBIO DE DIRECCI\u00d3N DE LA EMPRESA: RAPIDITO", "resumen": "LA EMPRESA RAPIDITO CON MATR\u00cdCULA DE COMERCIO: 00429150 ANUNCIA SU CAMBIO DE DIRECCI\u00d3N A: CALLE QUINTANILLA ZUAZO, N\u00b0 614, UNIDAD VECINAL: 0, MZA.: 0, EDIFICIO: 0, PISO: 0 , N\u00b0 DE OFICINA: 0  DE LA ZONA: PURA PURA, ENTRE LA CALLE REPUBLICA Y EX FABRICA SAID DENTRO DE SECOLAP", "fechaPublicacion": "2021-07-09T04:00:00.000Z", "empresa": {"matricula": null, "matriculaAnterior": "00429150", "razonSocial": "RAPIDITO"}, "fechaPublicacionFormato": "2021/07/09"}, {"id": "5711", "codigo": "PUB7K0845846", "titulo": "PUBLICACI\u00d3N DE LA MEMORIA ANUAL DE LA SOCIEDAD: \"PETROBRAS BOLIVIA S.A.\"", "resumen": "PUBLICACI\u00d3N DE LA MEMORIA ANUAL DE LA SOCIEDAD: \"PETROBRAS BOLIVIA S.A.\" DE LA GESTI\u00d3N: 2020", "fechaPublicacion": "2021-07-09T04:00:00.000Z", "empresa": {"matricula": "1028173027", "matriculaAnterior": "00013273", "razonSocial": "\"PETROBRAS BOLIVIA S.A.\""}, "fechaPublicacionFormato": "2021/07/09"}, {"id": "44827", "codigo": "CNV7KXO34997", "titulo": "NOTIFICACI\u00d3N DE CAMBIO DE DIRECCI\u00d3N DE LA EMPRESA:", "resumen": "LA EMPRESA GANODERMA EL BAJIO KM6 CON MATR\u00cdCULA DE COMERCIO: 00344048        ANUNCIA SU CAMBIO DE DIRECCI\u00d3N  A: AVENIDA LOS OLIVOS,         N\u00b0: 4, ENTRE CALLES: AV LOS OLIVOS Y CALLE EL BAJIO, UNIDAD VECINAL: 127, MZA.: 26 DE LA ZONA: EL BAJIO", "fechaPublicacion": "2021-07-09T04:00:00.000Z", "empresa": {"matricula": "6214237017", "matriculaAnterior": "00344048", "razonSocial": "GANODERMA EL BAJIO KM6"}, "fechaPublicacionFormato": "2021/07/09"}, {"id": "46598", "codigo": "CNVKKOF34997", "titulo": "NOTIFICACI\u00d3N DE CAMBIO DE DIRECCI\u00d3N DE LA EMPRESA:", "resumen": "LA EMPRESA CENTRO AUDIOLOGICO S.I.A.B. CON MATR\u00cdCULA DE COMERCIO: 00349622        ANUNCIA SU CAMBIO DE DIRECCI\u00d3N  A: CALLE WARNES,         N\u00b0: 677, ENTRE CALLES: ORURO Y COBIJA, UNIDAD VECINAL: 000A, MZA.: 0147, EDIFICIO: S/N, PISO: S/N, N\u00b0 DE OFICINA: S/N DE LA ZONA: BARRIO CASCO VIEJO", "fechaPublicacion": "2021-07-09T04:00:00.000Z", "empresa": {"matricula": "5861842016", "matriculaAnterior": "00349622", "razonSocial": "CENTRO AUDIOLOGICO S.I.A.B."}, "fechaPublicacionFormato": "2021/07/09"}, {"id": "76309", "codigo": "PUBZDJE45867", "titulo": "TRANSFERENCIA DE CUOTAS DE CAPITAL", "resumen": "ESCRITURA DE TRANSFERENCIA DE CUOTAS DE CAPITAL.", "fechaPublicacion": "2021-07-09T04:00:00.000Z", "empresa": {"matricula": "394421028", "matriculaAnterior": "00435014", "razonSocial": "TERANSECURITY S.R.L."}, "fechaPublicacionFormato": "2021/07/09"}, {"id": "81270", "codigo": "PUBXU3945914", "titulo": "CONSTITUCI\u00d3N DE SOCIEDAD COMERCIAL S.R.L. SOCIEDAD COLECTIVA O SOCIEDAD EN COMANDITA SIMPLE", "resumen": "TESTIMONIO DE CONSTITUCION DE SOCIEDAD COMERCIAL", "fechaPublicacion": "2021-07-09T04:00:00.000Z", "empresa": {"matricula": "408765027", "matriculaAnterior": "00450060", "razonSocial": "ALMENDRAS TOSCANA S.R.L."}, "fechaPublicacionFormato": "2021/07/09"}, {"id": "55159", "codigo": "PUBYWAD45881", "titulo": "MODIFICACI\u00d3N, ACLARACI\u00d3N Y/O COMPLEMENTACI\u00d3N DE LA CONSTITUCI\u00d3N DE SOCIEDAD COMERCIAL", "resumen": "MODIFICACION A LA DENOMINACION DE LA SOCIEDAD Y AL OBJETO SOCIAL.", "fechaPublicacion": "2021-07-09T04:00:00.000Z", "empresa": {"matricula": "346276020", "matriculaAnterior": "00376032", "razonSocial": "\"GRUPO INTERNACIONAL DE GESTION EMPRESARIAL GRIGEM LTDA\""}, "fechaPublicacionFormato": "2021/07/09"}, {"id": "81237", "codigo": "PUBTHX945857", "titulo": "CONSTITUCI\u00d3N DE SOCIEDAD COMERCIAL S.R.L. SOCIEDAD COLECTIVA O SOCIEDAD EN COMANDITA SIMPLE", "resumen": "TESTIMONIO DE CONSTITUCION DE SOCIEDAD DE RESPONSABILIDAD LIMITADA.", "fechaPublicacion": "2021-07-09T04:00:00.000Z", "empresa": {"matricula": "409560029", "matriculaAnterior": "00449938", "razonSocial": "IMPORTADORA BOLIVIAN CARGO UPSILON S.R.L."}, "fechaPublicacionFormato": "2021/07/09"}, {"id": "47795", "codigo": "CNV0GOM34994", "titulo": "NOTIFICACI\u00d3N DE CAMBIO DE DIRECCI\u00d3N DE LA EMPRESA: AMAS FLY S.R.L.", "resumen": "LA EMPRESA AMAS FLY S.R.L. CON MATR\u00cdCULA DE COMERCIO: 00353652 ANUNCIA SU CAMBIO DE DIRECCI\u00d3N A: AV. PERIMETRAL, N\u00b0 HANGAR N\u00b0 9  DE LA ZONA: AEROPUERTO EL TROMPILLO", "fechaPublicacion": "2021-07-09T04:00:00.000Z", "empresa": {"matricula": "330630021", "matriculaAnterior": "00353652", "razonSocial": "AMAS FLY S.R.L."}, "fechaPublicacionFormato": "2021/07/09"}, {"id": "15726", "codigo": "PUBEJWQ45888", "titulo": "PUBLICACI\u00d3N DE LA MEMORIA ANUAL DE LA SOCIEDAD: LABORATORIOS EUROFARMA BOLIVIA S.A.", "resumen": "PUBLICACI\u00d3N DE LA MEMORIA ANUAL DE LA SOCIEDAD: LABORATORIOS EUROFARMA BOLIVIA S.A. DE LA GESTI\u00d3N: 2020", "fechaPublicacion": "2021-07-09T04:00:00.000Z", "empresa": {"matricula": "146058022", "matriculaAnterior": "00130246", "razonSocial": "LABORATORIOS EUROFARMA BOLIVIA S.A."}, "fechaPublicacionFormato": "2021/07/09"}, {"id": "81241", "codigo": "PUBMWAH45860", "titulo": "CONSTITUCI\u00d3N DE SOCIEDAD COMERCIAL S.R.L. SOCIEDAD COLECTIVA O SOCIEDAD EN COMANDITA SIMPLE", "resumen": "TESTIMONIO DE CONSTITUCION DE SOCIEDAD DE RESPONSABILIDAD LIMITADA", "fechaPublicacion": "2021-07-09T04:00:00.000Z", "empresa": {"matricula": "409545027", "matriculaAnterior": "00449941", "razonSocial": "GRAIMAR S.R.L."}, "fechaPublicacionFormato": "2021/07/09"}, {"id": "81264", "codigo": "PUBUL5X45880", "titulo": "CONSTITUCI\u00d3N DE SOCIEDAD COMERCIAL S.R.L. SOCIEDAD COLECTIVA O SOCIEDAD EN COMANDITA SIMPLE", "resumen": "TESTIMONIO DE CONSTITUCION DE SOCIEDAD DE RESPONSABILIDAD LIMITADA.", "fechaPublicacion": "2021-07-09T04:00:00.000Z", "empresa": {"matricula": "407442023", "matriculaAnterior": "00450006", "razonSocial": "ROYALMIN S.R.L."}, "fechaPublicacionFormato": "2021/07/09"}, {"id": "81252", "codigo": "PUBKYJD45877", "titulo": "CONSTITUCI\u00d3N DE SOCIEDAD COMERCIAL S.R.L. SOCIEDAD COLECTIVA O SOCIEDAD EN COMANDITA SIMPLE", "resumen": "TESTIMONIO DE CONSTITUCION DE SOCIEDAD DE RESPONSABILIDAD LIMITADA", "fechaPublicacion": "2021-07-09T04:00:00.000Z", "empresa": {"matricula": "408662023", "matriculaAnterior": "00449975", "razonSocial": "RENALMED S.R.L."}, "fechaPublicacionFormato": "2021/07/09"}, {"id": "81243", "codigo": "PUBYHA945861", "titulo": "CONSTITUCI\u00d3N DE SOCIEDAD COMERCIAL S.R.L. SOCIEDAD COLECTIVA O SOCIEDAD EN COMANDITA SIMPLE", "resumen": "TESTIMONIO DE CONSTITUCION DE SOCIEDAD DE RESPONSABILIDAD LIMITADA", "fechaPublicacion": "2021-07-09T04:00:00.000Z", "empresa": {"matricula": "408903029", "matriculaAnterior": "00449942", "razonSocial": "LUKENJO S.R.L."}, "fechaPublicacionFormato": "2021/07/09"}, {"id": "4035", "codigo": "PUBDVPG45843", "titulo": "PUBLICACI\u00d3N DE BALANCE ANUAL PARA LA EMISI\u00d3N DE BONOS DE LA SOCIEDAD: DROGUERIA INTI S.A.", "resumen": "PUBLICACI\u00d3N DE BALANCE ANUAL PARA LA EMISI\u00d3N DE BONOS DE LA SOCIEDAD: DROGUERIA INTI S.A. DE LA GESTI\u00d3N:2021", "fechaPublicacion": "2021-07-09T04:00:00.000Z", "empresa": {"matricula": "1020521023", "matriculaAnterior": "00012821", "razonSocial": "DROGUERIA INTI S.A."}, "fechaPublicacionFormato": "2021/07/09"}, {"id": "81236", "codigo": "PUBX2CG45854", "titulo": "CONSTITUCI\u00d3N DE SOCIEDAD COMERCIAL S.R.L. SOCIEDAD COLECTIVA O SOCIEDAD EN COMANDITA SIMPLE", "resumen": "TESTIMONIO DE CONSTITUCION DE SOCIEDAD DE RESPONSABILIDAD LIMITADA", "fechaPublicacion": "2021-07-09T04:00:00.000Z", "empresa": {"matricula": "408752020", "matriculaAnterior": "00449933", "razonSocial": "DISTRICARS S.R.L."}, "fechaPublicacionFormato": "2021/07/09"}, {"id": "81255", "codigo": "PUBE6DP45883", "titulo": "CONSTITUCI\u00d3N DE SOCIEDAD COMERCIAL S.R.L. SOCIEDAD COLECTIVA O SOCIEDAD EN COMANDITA SIMPLE", "resumen": "TESTIMONIO DE CONSTITUCION DE SOCIEDAD COMERCIAL", "fechaPublicacion": "2021-07-09T04:00:00.000Z", "empresa": {"matricula": "410411022", "matriculaAnterior": "00449981", "razonSocial": "MGLOG INTERNATIONAL COMPANY S.R.L."}, "fechaPublicacionFormato": "2021/07/09"}, {"id": "67398", "codigo": "CNVSZEO34998", "titulo": "NOTIFICACI\u00d3N DE CAMBIO DE DIRECCI\u00d3N DE LA EMPRESA:", "resumen": "LA EMPRESA CENTRO DE DIAGNOSTICO IMAGSCAN S.R.L. CON MATR\u00cdCULA DE COMERCIO: 00410278        ANUNCIA SU CAMBIO DE DIRECCI\u00d3N  A: AVENIDA 14 DE SEPTIEMBRE A UNA CUADRA DE LA AVENIDA HERNANDO SILES,         N\u00b0: 5809, ENTRE CALLES: ENTRE CALLE 12 Y 13, UNIDAD VECINAL: S/N, MZA.: S/N, EDIFICIO: S/N, PISO: PLANTA BAJA, N\u00b0 DE OFICINA: S/N DE LA ZONA: OBRAJES", "fechaPublicacion": "2021-07-09T04:00:00.000Z", "empresa": {"matricula": "393884024", "matriculaAnterior": "00410278", "razonSocial": "CENTRO DE DIAGNOSTICO IMAGSCAN S.R.L."}, "fechaPublicacionFormato": "2021/07/09"}, {"id": "81244", "codigo": "PUBMZPK45868", "titulo": "CONSTITUCI\u00d3N DE SOCIEDAD COMERCIAL S.R.L. SOCIEDAD COLECTIVA O SOCIEDAD EN COMANDITA SIMPLE", "resumen": "TESTIMONIO DE CONSTITUCION DE SOCIEDAD COMERCIAL", "fechaPublicacion": "2021-07-09T04:00:00.000Z", "empresa": {"matricula": "408901027", "matriculaAnterior": "00449947", "razonSocial": "JIMAR BILLARES S.R.L."}, "fechaPublicacionFormato": "2021/07/09"}, {"id": "891", "codigo": "CNVI44J34997", "titulo": "CONVOCATORIA A ASAMBLEA ORDINARIA DE SOCIOS: SERVITEX VILLENA S.R.L.", "resumen": " CONVOCATORIA A LA ASAMBLEA GENERAL ORDINARIA DE SOCIOS  LA SOCIEDAD SERVITEX VILLENA S.R.L., DE ACUERDO A LO DISPUESTO POR EL ART\u00cdCULO 206 DEL C\u00d3DIGO DE COMERCIO DE BOLIVIA, CONVOCA A LA ASAMBLEA GENERAL ORDINARIA DE SOCIOS, QUE SE LLEVAR\u00c1 A CABO EL D\u00cdA 2021-07-20 A HORAS 15:00, EN EL DOMICILIO LEGAL DE LA SOCIEDAD, UBICADO EN OFICINA CENTRAL - AV. MCAL. SANTA CRUZ N\u00ba 1392 - MZ-1 OF-9 Y 10 DE LA CIUDAD DE LA PAZ DEL DEPARTAMENTO DE LA PAZ ESTADO PLURINACIONAL DE BOLIVIA, PARA CONSIDERAR EL SIGUIENTE ORDEN DEL D\u00cdA:  1.LECTURA DE LA ORDEN DEL D\u00cdA 2.ESTADO DE SITUACI\u00d3N FINANCIERA 3.ESTADO DE RESULTADOS 4.OTROS  ", "fechaPublicacion": "2021-07-09T04:00:00.000Z", "empresa": {"matricula": "1020243025", "matriculaAnterior": "00006981", "razonSocial": "SERVITEX VILLENA S.R.L."}, "fechaPublicacionFormato": "2021/07/09"}, {"id": "81263", "codigo": "PUBG7VM45896", "titulo": "CONSTITUCI\u00d3N DE SOCIEDAD COMERCIAL S.R.L. SOCIEDAD COLECTIVA O SOCIEDAD EN COMANDITA SIMPLE", "resumen": "TESTIMONIO DE CONSTITUCION DE SOCIEDAD DE RESPONSABILIDAD LIMITADA", "fechaPublicacion": "2021-07-09T04:00:00.000Z", "empresa": {"matricula": "411360023", "matriculaAnterior": "00450005", "razonSocial": "MARIDOSENALQUILER S.R.L."}, "fechaPublicacionFormato": "2021/07/09"}]}}