{"finalizado": true, "mensaje": "\u00a1Registro(s) obtenido(s) con \u00e9xito!", "datos": {"total": 103527, "filas": [{"id": "21085", "codigo": "PUBSDVQ03843", "titulo": "MODIFICACI\u00d3N, ACLARACI\u00d3N Y/O COMPLEMENTACI\u00d3N DE LA CONSTITUCI\u00d3N DE SOCIEDAD COMERCIAL", "resumen": "ESCRITURA PUBLICA DE MODIFICACION DE LA ESCRITURA CONSTITUTIVA Y ESTATUTOS", "fechaPublicacion": "2017-10-20T04:00:00.000Z", "empresa": {"matricula": "172508027", "matriculaAnterior": "00162774", "razonSocial": "MOTOLAND IMPORTACIONES SOCIEDAD ANONIMA"}, "fechaPublicacionFormato": "2017/10/20"}, {"id": "19150", "codigo": "PUBMJ2303819", "titulo": "PROYECTO DE DISTRIBUCI\u00d3N DE PATRIMONIO: CAT-FAM S.R.L.", "resumen": "PROYECTO DE DISTRIBUCI\u00d3N DE PATRIMONIO", "fechaPublicacion": "2017-10-20T04:00:00.000Z", "empresa": {"matricula": "167128029", "matriculaAnterior": "00151643", "razonSocial": "CAT-FAM S.R.L."}, "fechaPublicacionFormato": "2017/10/20"}, {"id": "12057", "codigo": "PUBVCBO03681", "titulo": "PUBLICACI\u00d3N DE LA MEMORIA ANUAL DE LA SOCIEDAD: EXIN INTEGRAL AGROPECUARIA S.A.", "resumen": "PUBLICACI\u00d3N DE LA MEMORIA ANUAL DE LA SOCIEDAD: EXIN INTEGRAL AGROPECUARIA S.A. DE LA GESTI\u00d3N: 2016", "fechaPublicacion": "2017-10-20T04:00:00.000Z", "empresa": {"matricula": "126515024", "matriculaAnterior": "00107656", "razonSocial": "EXIN INTEGRAL AGROPECUARIA S.A."}, "fechaPublicacionFormato": "2017/10/20"}, {"id": "45315", "codigo": "CNVIPQS00362", "titulo": "NOTIFICACION DE CAMBIO DE DIRECCION DE LA EMPRESA: SANDIA CREATIVA S.R.L.", "resumen": "LA EMPRESA SANDIA CREATIVA S.R.L. CON MATR\u00cdCULA DE COMERCIO: 00345546 ANUNCIA SU CAMBIO DE DIRECCI\u00d3N A: JAIME MENDOZA, N\u00b0H 22, EDIFICIO: TORRE GRAZIA, PISO: 5 , N\u00b0 DE OFICINA: 502  DE LA ZONA: SAN MIGUEL", "fechaPublicacion": "2017-10-20T04:00:00.000Z", "empresa": {"matricula": "309834024", "matriculaAnterior": "00345546", "razonSocial": "SANDIA CREATIVA S.R.L."}, "fechaPublicacionFormato": "2017/10/20"}, {"id": "19149", "codigo": "PUBEY5Q03820", "titulo": "DISOLUCI\u00d3N Y LIQUIDACI\u00d3N DE SOCIEDAD COMERCIAL", "resumen": "DISOLUCION, LIQUIDACION DE SOCIEDAD COMERCIAL Y CO                    ON DE MATRICULA DE COMERCIO", "fechaPublicacion": "2017-10-20T04:00:00.000Z", "empresa": {"matricula": "167128029", "matriculaAnterior": "00151643", "razonSocial": "CAT-FAM S.R.L."}, "fechaPublicacionFormato": "2017/10/20"}, {"id": "36301", "codigo": "CNVRWMA00368", "titulo": "NOTIFICACION DE CAMBIO DE DIRECCION DE LA EMPRESA: IMPRESIONES IMNOVA", "resumen": "LA EMPRESA IMPRESIONES IMNOVA CON MATR\u00cdCULA DE COMERCIO: 00296776 ANUNCIA SU CAMBIO DE DIRECCI\u00d3N A: CALLE MADRID, N\u00b0408  DE LA ZONA: EL MOLINO", "fechaPublicacion": "2017-10-20T04:00:00.000Z", "empresa": {"matricula": "7223025016", "matriculaAnterior": "00296776", "razonSocial": "IMPRESIONES IMNOVA"}, "fechaPublicacionFormato": "2017/10/20"}, {"id": "42428", "codigo": "PUB25TV03833", "titulo": "PROYECTO DE DISTRIBUCI\u00d3N DE PATRIMONIO: DECUS S.R.L.", "resumen": "PROYECTO DE DISTRIBUCI\u00d3N DE PATRIMONIO", "fechaPublicacion": "2017-10-20T04:00:00.000Z", "empresa": {"matricula": null, "matriculaAnterior": "00334659", "razonSocial": "DECUS S.R.L."}, "fechaPublicacionFormato": "2017/10/20"}, {"id": "35664", "codigo": "PUBYQ0W03858", "titulo": "MODIFICACI\u00d3N, ACLARACI\u00d3N Y/O COMPLEMENTACI\u00d3N DE LA CONSTITUCI\u00d3N DE SOCIEDAD COMERCIAL", "resumen": "ESCRITURA SOBRE AMPLIACION DEL OBJETO DE LA SOCIEDAD", "fechaPublicacion": "2017-10-20T04:00:00.000Z", "empresa": {"matricula": "277824029", "matriculaAnterior": "00290587", "razonSocial": "JMSNETWORKS BOLIVIA CO. LTDA."}, "fechaPublicacionFormato": "2017/10/20"}, {"id": "55571", "codigo": "PUBUX9I03822", "titulo": "CONSTITUCI\u00d3N DE SOCIEDAD COMERCIAL S.A., SOCIEDAD EN COMANDITA POR ACCIONES CONSTITUIDAS POR ACTO \u00daNICO, POR SUSCRIPCI\u00d3N P\u00daBLICA DE ACCIONES O CONSTITUCI\u00d3N DE SOCIEDAD DE ECONOM\u00cdA MIXTA", "resumen": "TESTIMONIO DE CONSTITUCION DE SOCIEDAD ANONIMA", "fechaPublicacion": "2017-10-20T04:00:00.000Z", "empresa": {"matricula": "345982022", "matriculaAnterior": "00376953", "razonSocial": "MINERA LIBRES ASOCIADOS S.A."}, "fechaPublicacionFormato": "2017/10/20"}, {"id": "55578", "codigo": "PUBXFFP03834", "titulo": "CONSTITUCI\u00d3N DE SOCIEDAD COMERCIAL S.R.L. SOCIEDAD COLECTIVA O SOCIEDAD EN COMANDITA SIMPLE", "resumen": "TESTIMONIO DE CONSTITUCION DE SOCIEDAD DE RESPONSABILIDAD LIMITADA", "fechaPublicacion": "2017-10-20T04:00:00.000Z", "empresa": {"matricula": "346813029", "matriculaAnterior": "00376979", "razonSocial": "DICONPRO INGENIEROS S.R.L."}, "fechaPublicacionFormato": "2017/10/20"}, {"id": "36394", "codigo": "PUBFGYP03828", "titulo": "TRANSFERENCIA DE CUOTAS DE CAPITAL", "resumen": "ESCRITURA PUBLICA DE TRANSFERENCIA DE CUOTAS DE CAPITAL, ADMISION DE NUEVO SOCIO Y CONSIGUIENTE MODIFICACION AL TESTIMONIO DE CONSTITUCION", "fechaPublicacion": "2017-10-20T04:00:00.000Z", "empresa": {"matricula": "283092028", "matriculaAnterior": "00297742", "razonSocial": "FOBB S.R.L."}, "fechaPublicacionFormato": "2017/10/20"}, {"id": "47648", "codigo": "CNV7A2900364", "titulo": "NOTIFICACION DE CAMBIO DE DIRECCION DE LA EMPRESA: DERMASPA", "resumen": "LA EMPRESA DERMASPA CON MATR\u00cdCULA DE COMERCIO: 00353198 ANUNCIA SU CAMBIO DE DIRECCI\u00d3N A: AV. SAN MARTIN , N\u00b0S/N, MZA.: 003A, EDIFICIO: SAN MARTIN, PISO: 6 , N\u00b0 DE OFICINA: DPTO. 6A  DE LA ZONA: BARRIO EQUIPETROL", "fechaPublicacion": "2017-10-20T04:00:00.000Z", "empresa": {"matricula": "3897968013", "matriculaAnterior": "00353198", "razonSocial": "DERMASPA"}, "fechaPublicacionFormato": "2017/10/20"}, {"id": "7666", "codigo": "PUB6SFL03825", "titulo": "MODIFICACI\u00d3N, ACLARACI\u00d3N Y/O COMPLEMENTACI\u00d3N DE LA CONSTITUCI\u00d3N DE SOCIEDAD COMERCIAL", "resumen": "ESCRITURA SOBRE CAMBIO DE DENOMINACION SOCIAL Y CONSECUENTE MODIFICACION PARCIAL DE LA ESCRITURA DE CONSTITUCION Y ESTATUTOS", "fechaPublicacion": "2017-10-20T04:00:00.000Z", "empresa": {"matricula": "1028239028", "matriculaAnterior": "00013796", "razonSocial": "PAMPA ENERGIA BOLIVIA S.A."}, "fechaPublicacionFormato": "2017/10/20"}, {"id": "12083", "codigo": "PUBO5ZV03855", "titulo": "TRANSFERENCIA DE CUOTAS DE CAPITAL", "resumen": "TRANSFERENCIA DE CUOTAS DE CAPITAL", "fechaPublicacion": "2017-10-20T04:00:00.000Z", "empresa": {"matricula": "1011535029", "matriculaAnterior": "00107841", "razonSocial": "INNOVACION S.R.L."}, "fechaPublicacionFormato": "2017/10/20"}, {"id": "55579", "codigo": "PUB3D5303832", "titulo": "CONSTITUCI\u00d3N DE SOCIEDAD COMERCIAL S.R.L. SOCIEDAD COLECTIVA O SOCIEDAD EN COMANDITA SIMPLE", "resumen": "TESTIMONIO DE CONSTITUCION DE SOCIEDAD DE RESPONSABILIDAD LIMITADA", "fechaPublicacion": "2017-10-20T04:00:00.000Z", "empresa": {"matricula": "346856023", "matriculaAnterior": "00376980", "razonSocial": "INNOVACION Y DESARROLLO TECNOLOGICO VIAL S.R.L."}, "fechaPublicacionFormato": "2017/10/20"}, {"id": "55597", "codigo": "PUBE2PV03864", "titulo": "CONSTITUCI\u00d3N DE SOCIEDAD COMERCIAL S.R.L. SOCIEDAD COLECTIVA O SOCIEDAD EN COMANDITA SIMPLE", "resumen": "ESCRITURA PUBLICA DE ACLARATIVA AL TESTIMONIO DE CONSTITUCION", "fechaPublicacion": "2017-10-20T04:00:00.000Z", "empresa": {"matricula": "346821024", "matriculaAnterior": "00377016", "razonSocial": "AIR PLUS S.R.L."}, "fechaPublicacionFormato": "2017/10/20"}, {"id": "55581", "codigo": "PUBMAYJ03835", "titulo": "CONSTITUCI\u00d3N DE SOCIEDAD COMERCIAL S.R.L. SOCIEDAD COLECTIVA O SOCIEDAD EN COMANDITA SIMPLE", "resumen": "TESTIMONIO DE CONSTITUCION DE SOCIEDAD DE RESPONSABILIDAD LIMITADA.", "fechaPublicacion": "2017-10-20T04:00:00.000Z", "empresa": {"matricula": "346600021", "matriculaAnterior": "00376981", "razonSocial": "\"E.C.E.F. LTDA. EMPRESA DE COMERCIO EXTERIOR FRANCO\""}, "fechaPublicacionFormato": "2017/10/20"}, {"id": "55593", "codigo": "PUB4G2W03857", "titulo": "CONSTITUCI\u00d3N DE SOCIEDAD COMERCIAL S.A., SOCIEDAD EN COMANDITA POR ACCIONES CONSTITUIDAS POR ACTO \u00daNICO, POR SUSCRIPCI\u00d3N P\u00daBLICA DE ACCIONES O CONSTITUCI\u00d3N DE SOCIEDAD DE ECONOM\u00cdA MIXTA", "resumen": "TESTIMONIO DE CONSTITUCION DE SOCIEDAD ANONIMA", "fechaPublicacion": "2017-10-20T04:00:00.000Z", "empresa": {"matricula": "345979028", "matriculaAnterior": "00377009", "razonSocial": "PRESTAMOS INVERSIONES - PARA EL DESARROLLO EMPRESARIAL S.A. PODER S.A."}, "fechaPublicacionFormato": "2017/10/20"}, {"id": "55586", "codigo": "PUB2UTG03850", "titulo": "CONSTITUCI\u00d3N DE SOCIEDAD COMERCIAL S.R.L. SOCIEDAD COLECTIVA O SOCIEDAD EN COMANDITA SIMPLE", "resumen": "TESTIMONIO DE CONSTITUCION DE SOCIEDAD DE RESPONSABILIDAD LIMITADA.", "fechaPublicacion": "2017-10-20T04:00:00.000Z", "empresa": {"matricula": "346316025", "matriculaAnterior": "00376996", "razonSocial": "SATVA S.R.L."}, "fechaPublicacionFormato": "2017/10/20"}, {"id": "15463", "codigo": "PUBC2BS03824", "titulo": "REDUCCI\u00d3N DE CAPITAL SOCIAL", "resumen": "ESCRITURA SOBRE DISMINUCION DE CAPITAL SOCIAL Y MODIFICACION DEL VALOR NOMINAL DE LAS CUOTAS DE CAPITAL", "fechaPublicacion": "2017-10-20T04:00:00.000Z", "empresa": {"matricula": "146292028", "matriculaAnterior": "00128434", "razonSocial": "INFORFACTORY SERVICIOS INFORMATICOS S.R.L."}, "fechaPublicacionFormato": "2017/10/20"}, {"id": "12580", "codigo": "PUBIK8303854", "titulo": "MODIFICACI\u00d3N, ACLARACI\u00d3N Y/O COMPLEMENTACI\u00d3N DE LA CONSTITUCI\u00d3N DE SOCIEDAD COMERCIAL", "resumen": "ESCRITURA PUBLICA DE INCREMENTO DE CAPITAL A LA SUMA DE BS. 400.000.- Y MODIFICACION DE UNA PARTE DE LA CLAUSULA DECIMA TERCERA, SUSCRITA POR  LOS SOCIOS DE LA EMPRESA MINERA ELECTRICA Y CONSTRUCCION S.R.L. MINELCO S.R.L.", "fechaPublicacion": "2017-10-20T04:00:00.000Z", "empresa": {"matricula": "123323026", "matriculaAnterior": "00110156", "razonSocial": "EMPRESA MINERA ELECTRICA Y CONSTRUCCION S.R.L. MINELCO S.R.L."}, "fechaPublicacionFormato": "2017/10/20"}, {"id": "55583", "codigo": "PUB833Z03838", "titulo": "CONSTITUCI\u00d3N DE SOCIEDAD COMERCIAL S.R.L. SOCIEDAD COLECTIVA O SOCIEDAD EN COMANDITA SIMPLE", "resumen": "TESTIMONIO DE CONSTITUCION DE SOCIEDAD DE RESPONSABILIDAD LIMITADA", "fechaPublicacion": "2017-10-20T04:00:00.000Z", "empresa": {"matricula": null, "matriculaAnterior": "00376990", "razonSocial": "ROWELL TECHNOLOGY S.R.L."}, "fechaPublicacionFormato": "2017/10/20"}, {"id": "17614", "codigo": "PUBDKTA03844", "titulo": "AUMENTO DE CAPITAL SOCIAL", "resumen": "ESCRITURA PUBLICA DE AUMENTO DE CAPITAL A LA SUMA DE BS. 4.000.000.-  Y CONSIGUIENTE MODIFICACION DE LA ESCRITURA DE CONSTITUCION", "fechaPublicacion": "2017-10-20T04:00:00.000Z", "empresa": {"matricula": "157244025", "matriculaAnterior": "00141535", "razonSocial": "CORRESUR S.R.L."}, "fechaPublicacionFormato": "2017/10/20"}, {"id": "55582", "codigo": "PUBI1F403836", "titulo": "CONSTITUCI\u00d3N DE SOCIEDAD COMERCIAL S.R.L. SOCIEDAD COLECTIVA O SOCIEDAD EN COMANDITA SIMPLE", "resumen": "TESTIMONIO DE CONSTITUCION DE SOCIEDAD DE RESPONSABILIDAD LIMITADA", "fechaPublicacion": "2017-10-20T04:00:00.000Z", "empresa": {"matricula": "346885028", "matriculaAnterior": "00376986", "razonSocial": "CONSTRUCCIONES IL VIVAIO S.R.L."}, "fechaPublicacionFormato": "2017/10/20"}, {"id": "55596", "codigo": "PUBVYE603863", "titulo": "CONSTITUCI\u00d3N DE SOCIEDAD COMERCIAL S.R.L. SOCIEDAD COLECTIVA O SOCIEDAD EN COMANDITA SIMPLE", "resumen": "TESTIMONIO DE CONSTITUCION DE SOCIEDAD COMERCIAL", "fechaPublicacion": "2017-10-20T04:00:00.000Z", "empresa": {"matricula": "346821024", "matriculaAnterior": "00377016", "razonSocial": "AIR PLUS S.R.L."}, "fechaPublicacionFormato": "2017/10/20"}, {"id": "55588", "codigo": "PUBCV5K03849", "titulo": "CONSTITUCI\u00d3N DE SOCIEDAD COMERCIAL S.R.L. SOCIEDAD COLECTIVA O SOCIEDAD EN COMANDITA SIMPLE", "resumen": "TESTIMONIO DE CONSTITUCION DE SOCIEDAD COMERCIAL", "fechaPublicacion": "2017-10-20T04:00:00.000Z", "empresa": {"matricula": "346807022", "matriculaAnterior": "00376999", "razonSocial": "CONSTRULATIN S.R.L."}, "fechaPublicacionFormato": "2017/10/20"}, {"id": "25034", "codigo": "PUBEJC203859", "titulo": "TRANSFERENCIA DE CUOTAS DE CAPITAL", "resumen": "TRANSFERENCIA DE CUOTAS DE CAPITAL", "fechaPublicacion": "2017-10-20T04:00:00.000Z", "empresa": {"matricula": "190154025", "matriculaAnterior": "00186532", "razonSocial": "ALLMET COMERCIAL INDUSTRIAL AGROPECUARIA S.R.L."}, "fechaPublicacionFormato": "2017/10/20"}, {"id": "55572", "codigo": "PUB6TU503826", "titulo": "CONSTITUCI\u00d3N DE SOCIEDAD COMERCIAL S.A., SOCIEDAD EN COMANDITA POR ACCIONES CONSTITUIDAS POR ACTO \u00daNICO, POR SUSCRIPCI\u00d3N P\u00daBLICA DE ACCIONES O CONSTITUCI\u00d3N DE SOCIEDAD DE ECONOM\u00cdA MIXTA", "resumen": "TESTIMONIO DE CONSTITUCION DE SOCIEDAD ANONIMA", "fechaPublicacion": "2017-10-20T04:00:00.000Z", "empresa": {"matricula": "346000020", "matriculaAnterior": "00376970", "razonSocial": "INVERSIONES LOSSUAR S.A."}, "fechaPublicacionFormato": "2017/10/20"}, {"id": "31254", "codigo": "CNVG1A600363", "titulo": "NOTIFICACION DE CAMBIO DE DIRECCION DE LA EMPRESA: FAINABOL FABRICA INDUSTRIALIZADORA DE ALIMENTOS BOLIVIA", "resumen": "LA EMPRESA FAINABOL FABRICA INDUSTRIALIZADORA DE ALIMENTOS BOLIVIA CON MATR\u00cdCULA DE COMERCIO: 00237262 ANUNCIA SU CAMBIO DE DIRECCI\u00d3N A: CALLE/ ECUADOR, N\u00b0935  DE LA ZONA: 4 DE JULIO", "fechaPublicacion": "2017-10-20T04:00:00.000Z", "empresa": {"matricula": "237262", "matriculaAnterior": "00237262", "razonSocial": "FAINABOL FABRICA INDUSTRIALIZADORA DE ALIMENTOS BOLIVIA"}, "fechaPublicacionFormato": "2017/10/20"}, {"id": "55591", "codigo": "PUBOOYK03856", "titulo": "CONSTITUCI\u00d3N DE SOCIEDAD COMERCIAL S.R.L. SOCIEDAD COLECTIVA O SOCIEDAD EN COMANDITA SIMPLE", "resumen": "TESTIMONIO DE CONSTITUCION DE SOCIEDAD DE RESPONSABILIDAD LIMITADA.", "fechaPublicacion": "2017-10-20T04:00:00.000Z", "empresa": {"matricula": "346849028", "matriculaAnterior": "00377008", "razonSocial": "EMPRESA GNF S.R.L."}, "fechaPublicacionFormato": "2017/10/20"}, {"id": "49149", "codigo": "PUBQDL903827", "titulo": "MODIFICACI\u00d3N, ACLARACI\u00d3N Y/O COMPLEMENTACI\u00d3N DE LA CONSTITUCI\u00d3N DE SOCIEDAD COMERCIAL", "resumen": "MODIFICACION A LA CONSTITUCION POR AMPLIACION DEL OBJETO SOCIAL.", "fechaPublicacion": "2017-10-20T04:00:00.000Z", "empresa": {"matricula": "329480020", "matriculaAnterior": "00358688", "razonSocial": "CENTRO DEPORTIVO SPORTMOTION S.R.L."}, "fechaPublicacionFormato": "2017/10/20"}, {"id": "14630", "codigo": "PUBQ9I303848", "titulo": "TRANSFERENCIA DE CUOTAS DE CAPITAL", "resumen": "TRANSFERENCIA DE CUOTAS DE CAPITAL", "fechaPublicacion": "2017-10-20T04:00:00.000Z", "empresa": {"matricula": "143109028", "matriculaAnterior": "00123248", "razonSocial": "KAWAMOTO S.R.L."}, "fechaPublicacionFormato": "2017/10/20"}, {"id": "51061", "codigo": "PUBHDU003852", "titulo": "AUMENTO DE CAPITAL SOCIAL", "resumen": "INSTRUMENTO PUBLICO SOBRE AUMENTO DE CAPITAL.", "fechaPublicacion": "2017-10-20T04:00:00.000Z", "empresa": {"matricula": "332734028", "matriculaAnterior": "00365587", "razonSocial": "AGROPECUARIA EL GERAR S.R.L."}, "fechaPublicacionFormato": "2017/10/20"}, {"id": "55584", "codigo": "PUB50KN03842", "titulo": "CONSTITUCI\u00d3N DE SOCIEDAD COMERCIAL S.R.L. SOCIEDAD COLECTIVA O SOCIEDAD EN COMANDITA SIMPLE", "resumen": "ACLARACION, MODIFICACION Y/O COMPLEMENTACION", "fechaPublicacion": "2017-10-20T04:00:00.000Z", "empresa": {"matricula": "346246029", "matriculaAnterior": "00376991", "razonSocial": "REINA VICTORIA S.R.L."}, "fechaPublicacionFormato": "2017/10/20"}, {"id": "27566", "codigo": "PUB7L3H03845", "titulo": "AUMENTO DE CAPITAL SOCIAL", "resumen": "ESCRITURA PUBLICA DE MODIFICACION AL VALOR DE CUOTAS DE CAPITAL, AUMENTO DE CAPITAL A BS. 560.000.- Y CONSIGUIENTE MODIFICACION A LA ESCRITURA DE CONSTITUCION", "fechaPublicacion": "2017-10-20T04:00:00.000Z", "empresa": {"matricula": "198908021", "matriculaAnterior": "00201967", "razonSocial": "IMPORTACIONES YORUBA S.R.L."}, "fechaPublicacionFormato": "2017/10/20"}, {"id": "6065", "codigo": "PUB1YNL03861", "titulo": "MODIFICACI\u00d3N, ACLARACI\u00d3N Y/O COMPLEMENTACI\u00d3N DE LA CONSTITUCI\u00d3N DE SOCIEDAD COMERCIAL", "resumen": "MODIFICACION A LOS ESTATUTOS", "fechaPublicacion": "2017-10-20T04:00:00.000Z", "empresa": {"matricula": "1020757027", "matriculaAnterior": "00013332", "razonSocial": "PIL ANDINA S.A."}, "fechaPublicacionFormato": "2017/10/20"}, {"id": "40714", "codigo": "PUBQYYJ03851", "titulo": "MODIFICACI\u00d3N, ACLARACI\u00d3N Y/O COMPLEMENTACI\u00d3N DE LA CONSTITUCI\u00d3N DE SOCIEDAD COMERCIAL", "resumen": "ESCRITURA PUBLICA SOBRE MODIFICACION AL OBJETO DE LA EMPRESA.", "fechaPublicacion": "2017-10-20T04:00:00.000Z", "empresa": {"matricula": "297114028", "matriculaAnterior": "00327584", "razonSocial": "ALIMPORCON S.R.L."}, "fechaPublicacionFormato": "2017/10/20"}, {"id": "18869", "codigo": "PUBMOTT03839", "titulo": "MODIFICACI\u00d3N, ACLARACI\u00d3N Y/O COMPLEMENTACI\u00d3N DE LA CONSTITUCI\u00d3N DE SOCIEDAD COMERCIAL", "resumen": "MODIFICACION A LA CONSTITUCION, TRANSFERENCIA DE CUOTAS DE CAPITAL, RETIRO, E INGRESO VOLUNTARIO DE SOCIOS.", "fechaPublicacion": "2017-10-20T04:00:00.000Z", "empresa": {"matricula": "164774025", "matriculaAnterior": "00149081", "razonSocial": "EMPRESA CONSTRUCTORA Y CONSULTORA VIRGEN DE REMEDIOS S.R.L."}, "fechaPublicacionFormato": "2017/10/20"}, {"id": "55573", "codigo": "PUBXBSQ03829", "titulo": "CONSTITUCI\u00d3N DE SOCIEDAD COMERCIAL S.R.L. SOCIEDAD COLECTIVA O SOCIEDAD EN COMANDITA SIMPLE", "resumen": "TESTIMONIO DE CONSTITUCION DE SOCIEDAD DE RESPONSABILIDAD LIMITADA", "fechaPublicacion": "2017-10-20T04:00:00.000Z", "empresa": {"matricula": "346815020", "matriculaAnterior": "00376972", "razonSocial": "MRI PROFILE S.R.L."}, "fechaPublicacionFormato": "2017/10/20"}, {"id": "18870", "codigo": "PUBI5PR03840", "titulo": "MODIFICACI\u00d3N, ACLARACI\u00d3N Y/O COMPLEMENTACI\u00d3N DE LA CONSTITUCI\u00d3N DE SOCIEDAD COMERCIAL", "resumen": "MODIFICACION A LA CONSTITUCION, MODIFICACION A LA DENOMINACION, AMPLIACION DE OBJETO Y AUMENTO DE CAPITAL A BS. 210.000", "fechaPublicacion": "2017-10-20T04:00:00.000Z", "empresa": {"matricula": "164774025", "matriculaAnterior": "00149081", "razonSocial": "EMPRESA CONSTRUCTORA Y CONSULTORA VIRGEN DE REMEDIOS S.R.L."}, "fechaPublicacionFormato": "2017/10/20"}, {"id": "55585", "codigo": "PUB65I803841", "titulo": "CONSTITUCI\u00d3N DE SOCIEDAD COMERCIAL S.R.L. SOCIEDAD COLECTIVA O SOCIEDAD EN COMANDITA SIMPLE", "resumen": "TESTIMONIO DE CONSTITUCION DE SOCIEDAD DE RESPONSABILIDAD LIMITADA", "fechaPublicacion": "2017-10-20T04:00:00.000Z", "empresa": {"matricula": "346246029", "matriculaAnterior": "00376991", "razonSocial": "REINA VICTORIA S.R.L."}, "fechaPublicacionFormato": "2017/10/20"}, {"id": "26200", "codigo": "PUBJ9L903837", "titulo": "TRANSFORMACI\u00d3N", "resumen": "ESCRITURA PUBLICA DE TRANSFORMACION DE EMPRESA UNIPERSONAL A SOCIEDAD DE RESPONSABILIDAD LIMITADA", "fechaPublicacion": "2017-10-20T04:00:00.000Z", "empresa": {"matricula": "346695021", "matriculaAnterior": "00192055", "razonSocial": "COMECBOL S.R.L."}, "fechaPublicacionFormato": "2017/10/20"}, {"id": "35881", "codigo": "CNV8E4L00367", "titulo": "NOTIFICACION DE CAMBIO DE DIRECCION DE LA EMPRESA: KITSUNEGAS", "resumen": "LA EMPRESA KITSUNEGAS CON MATR\u00cdCULA DE COMERCIO: 00293071 ANUNCIA SU CAMBIO DE DIRECCI\u00d3N A: CELSO CAMACHO, N\u00b058, UNIDAD VECINAL: BARRIO MORITA, MZA.: 14, EDIFICIO: KITSUNEIPC, PISO: 1 ER PISO , N\u00b0 DE OFICINA: 01  DE LA ZONA: TRANSITO", "fechaPublicacion": "2017-10-20T04:00:00.000Z", "empresa": {"matricula": "7849168013", "matriculaAnterior": "00293071", "razonSocial": "KITSUNE IPC"}, "fechaPublicacionFormato": "2017/10/20"}, {"id": "37723", "codigo": "CNV2OFJ00359", "titulo": "NOTIFICACION DE CAMBIO DE DIRECCION DE LA EMPRESA: ELECTRIC SYSTEM Y EMME2 DESING BOLIVIA", "resumen": "LA EMPRESA ELECTRIC SYSTEM Y EMME2 DESING BOLIVIA CON MATR\u00cdCULA DE COMERCIO: 00310318 ANUNCIA SU CAMBIO DE DIRECCI\u00d3N A: C/ DR GERMAN ZEGARRA, N\u00b07, UNIDAD VECINAL: 0053, MZA.: 0001, PISO: 102  DE LA ZONA: B/UNIVERSITARIO", "fechaPublicacion": "2017-10-19T04:00:00.000Z", "empresa": {"matricula": "6280634018", "matriculaAnterior": "00310318", "razonSocial": "ELECTRIC SYSTEM Y EMME2 DESING BOLIVIA"}, "fechaPublicacionFormato": "2017/10/19"}, {"id": "55555", "codigo": "PUBEHCE03794", "titulo": "CONSTITUCI\u00d3N DE SOCIEDAD COMERCIAL S.R.L. SOCIEDAD COLECTIVA O SOCIEDAD EN COMANDITA SIMPLE", "resumen": "TESTIMONIO DE CONSTITUCION DE SOCIEDAD COMERCIAL", "fechaPublicacion": "2017-10-19T04:00:00.000Z", "empresa": {"matricula": "350761028", "matriculaAnterior": "00376882", "razonSocial": "ARIBIBIS SRL"}, "fechaPublicacionFormato": "2017/10/19"}, {"id": "55543", "codigo": "PUB6KIT03787", "titulo": "CONSTITUCI\u00d3N DE SOCIEDAD COMERCIAL S.R.L. SOCIEDAD COLECTIVA O SOCIEDAD EN COMANDITA SIMPLE", "resumen": "TESTIMONIO DE CONSTITUCION DE SOCIEDAD DE RESPONSABILIDAD LIMITADA", "fechaPublicacion": "2017-10-19T04:00:00.000Z", "empresa": {"matricula": "372266027", "matriculaAnterior": "00376862", "razonSocial": "GO SMART TECHNOLOGIES S.R.L."}, "fechaPublicacionFormato": "2017/10/19"}, {"id": "8837", "codigo": "PUBAF0I03817", "titulo": "MODIFICACI\u00d3N, ACLARACI\u00d3N Y/O COMPLEMENTACI\u00d3N DE LA CONSTITUCI\u00d3N DE SOCIEDAD COMERCIAL", "resumen": "MODIFICACION TOTAL DE LA ESCRITURA CONSTITUTIVA.", "fechaPublicacion": "2017-10-19T04:00:00.000Z", "empresa": {"matricula": "144166029", "matriculaAnterior": "00040979", "razonSocial": "AGRICOLA \"LA LIBERTAD\" LTDA."}, "fechaPublicacionFormato": "2017/10/19"}, {"id": "55561", "codigo": "PUBR87B03804", "titulo": "CONSTITUCI\u00d3N DE SOCIEDAD COMERCIAL S.R.L. SOCIEDAD COLECTIVA O SOCIEDAD EN COMANDITA SIMPLE", "resumen": "TESTIMONIO DE CONSTITUCION DE SOCIEDAD DE RESPONSABILIDAD LIMITADA", "fechaPublicacion": "2017-10-19T04:00:00.000Z", "empresa": {"matricula": null, "matriculaAnterior": "00376899", "razonSocial": "EMPRESA SETHOS S.R.L."}, "fechaPublicacionFormato": "2017/10/19"}, {"id": "12980", "codigo": "PUB3FHV03814", "titulo": "TRANSFERENCIA DE CUOTAS DE CAPITAL", "resumen": "ESCRITURA PUBLICA DE TRANSFERENCIA DE CUOTAS DE CAPITAL Y MODIFICACION DE ESCRITURA DE CONSTITUCION.", "fechaPublicacion": "2017-10-19T04:00:00.000Z", "empresa": {"matricula": "128153028", "matriculaAnterior": "00113014", "razonSocial": "INDUSTRIALIZADORA DE CACAO DE EXPORTACION S.R.L. \"INCADEX S.R.L.\""}, "fechaPublicacionFormato": "2017/10/19"}, {"id": "50236", "codigo": "PUBQYS003816", "titulo": "AUMENTO DE CAPITAL SOCIAL", "resumen": "AUMENTO DE CAPITAL SOCIAL", "fechaPublicacion": "2017-10-19T04:00:00.000Z", "empresa": {"matricula": "331158023", "matriculaAnterior": "00362410", "razonSocial": "L&B S.R.L."}, "fechaPublicacionFormato": "2017/10/19"}]}}